Workbook

Sheet Lisez-moi
A1: TAIRO — MODÈLE FINANCIER 3 ÉTATS (P&L, trésorerie, bilan)
A3: OBJET
A4: Modélisation financière 3 ans (M1–M36) de la startup Tairo — marketplace de services (Ampio),
A5: location de matériel (Ampindramo) et formation vidéo (Ampianaro) à Madagascar. Devise : Ariary (MGA), hors taxes.
A7: MODÈLE ÉCONOMIQUE
A8: 1. Abonnement prestataire Ampio+ : 24 000 Ar/mois (indexé), souscrit par une part paramétrable des prestataires actifs (10 % par défaut).
A9: 2. Commissions sur prestations, prélevées sur le prestataire : 10 % (Plomberie, Mécanique, Électricité, Jardinage,
A10: Agriculture, Ménage, Irakiraka, Bricolage, BTP, Couture), 15 % (Cuisine), 20 % (Déménagement),
A11: 25 % (Informatique, Transport, Evénementiel, Animaux, Arts, Musiques) — mix paramétrable dans Parametres.
A12: 3. Location entre particuliers : 13 % sur le loueur (caution non commissionnée).
A13: 4. Location professionnelle : paliers sur le total — 30 % (≤ 25 000 Ar), 20 % (25 001–45 000 Ar), 15 % (> 45 000 Ar).
A14: 5. Mise en ligne de vidéos Ampianaro B2B : 64 000 Ar/mois par client professionnel.
... A63: PLANCHER DE CAISSE : lire Financement, bloc « Validation 3 ans » — pic de besoin cumulé avant financement, trésorerie minimale après service de la dette, couverture OK / INSUFFISANT et financement externe minimum indicatif. Leviers : apport (Parametres!B139), mois financés / sécurité (B140, B141), durée de l'emprunt (B144), budget publicité (section 9), salaires (section 13).

Sheet Dashboard
A1: DASHBOARD — Tairo, modèle 3 états (MGA)
A2: Scénario actif : | B2: =Parametres!B3 -> Base
A4: ACTIVITÉ
A5: Chiffre d'affaires Année 1 | B5: ='P&L'!B30 -> 21706621
A6: Chiffre d'affaires Année 2 | B6: ='P&L'!C30 -> 38087024
A7: Chiffre d'affaires Année 3 | B7: ='P&L'!D30 -> 63455216
A8: Croissance CA A2 / A1 | B8: =KPI!C58 -> 0.75462707
A9: Croissance CA A3 / A2 | B9: =KPI!D58 -> 0.66605866
A10: GMV Année 3 | B10: =KPI!D51 -> 77839858
A11: Take rate moyen Année 3 | B11: =KPI!D53 -> 0.14343777
A12: MRR fin Année 3 | B12: =KPI!D54 -> 5294358.1
A13: ARR fin Année 3 | B13: =KPI!D54*12 -> 63532297
A15: RENTABILITÉ
A16: Marge de contribution Année 3 | B16: =IFERROR(SUM(Contribution!Z12:AK12)/SUM(Contribution!Z5:AK5),0) -> 0.8883578
A17: EBITDA Année 3 | B17: ='P&L'!D31 -> 8893982.1
A18: Résultat net Année 1 | B18: ='P&L'!B35 -> -21609440
A19: Résultat net Année 2 | B19: ='P&L'!C35 -> -9978577.1
A20: Résultat net Année 3 | B20: ='P&L'!D35 -> 2560744
A21: Seuil de rentabilité mensuel (CA, moyenne 36 mois) | B21: =-AVERAGE('P&L'!B17:AK17)/AVERAGE('P&L'!B9:AK9) -> 3845081.3
A22: Premier mois EBITDA > 0 | B22: =IFERROR(MATCH(TRUE(),INDEX('P&L'!B18:AK18>0,0),0),"> 36 mois") -> 22
A23: Premier mois de résultat net cumulé positif | B23: =IFERROR(MATCH(TRUE(),INDEX('Base graphique'!B8:AK8>0,0),0),"> 36 mois") -> > 36 mois
A25: UNIT ECONOMICS & OFFRE
A26: CAC offre Année 3 | B26: =KPI!D63 -> 32325.363
A27: CAC demande Année 3 | B27: =KPI!D64 -> 22872.079
A28: LTV / CAC offre fin A3 (cible > 3, LTV bornée 36 mois) | B28: =KPI!D65 -> 5.7660133
A29: LTV / CAC demande fin A3 (cible > 3) | B29: =KPI!D66 -> 15.043695
A30: Prestataires Ampio actifs fin A3 | B30: =KPI!D59 -> 121.62289
A31: Utilisation capacité Ampio fin A3 (alerte si ≥ fill rate max) | B31: =KPI!D60 -> 0.1663472
A32: GMV perdu faute d'offre sur 3 ans | B32: =SUM(KPI!B61:D61) -> 0
A33: Mois d'activation collaborateur 2 (ou > 36) | B33: =IFERROR(MATCH(1,'Plan ventes'!B70:AK70,0),"> 36 mois") -> 25
A35: FINANCEMENT & TRÉSORERIE
A36: Besoin de financement initial (CAPEX + démarrage + sécurité) | B36: =Financement!B11 -> 52008307
A37: Apport en fonds propres | B37: =Financement!B14 -> 9000000
A38: ASK — financement externe recherché | B38: =Financement!B18 -> 43008307
A39: dont equity / quasi-fonds propres (indicatif) | B39: =Financement!B19 -> 12902492
A40: dont dette (indicatif) — modélisé en emprunt | B40: =Financement!B20 -> 30105815
A41: Mensualité de l'emprunt | B41: =Financement!B26 -> 892781.72
A42: Trésorerie fin Année 3 | B42: =Tresorerie!AM25 -> -2445043.6
A43: Trésorerie minimale sur 36 mois | B43: =Financement!B39 -> -2445043.6
A44: Cible : matelas de sécurité | B44: =Financement!B10 -> 8416749
A45: Couverture du matelas de sécurité | B45: =Financement!B40 -> INSUFFISANT — augmenter apport, mois financés ou durée
A46: Capital restant dû fin M36 | B46: =Financement!B44 -> 19542230
A47: Taux de liquidité fin A3 (cible > 1) | B47: =INDEX(KPI!B47:AK47,1,36) -> -0.17607797
A49: CONTRÔLES
A50: Rule of 40 Année 3 (indicatif, base petite) | B50: =KPI!D67 -> 0.80622022
A51: Contrôle bilan max |écart| (Ar) | B51: =MAX(ABS(Bilan!C18),ABS(Bilan!AM18)) -> 1.1175871e-08
A52: Contrôle contribution vs P&L max |écart| (Ar) | B52: =MAX(ABS(MIN(Contribution!B20:AK20)),ABS(MAX(Contribution!B20:AK20))) -> 0
A53: Contrôle mix take rate prestations (doit = 100 %) | B53: =Parametres!$D$14 -> 1

Sheet Parametres
A1: TAIRO — HYPOTHÈSES (MGA HT) — MODÈLE 3 ÉTATS
A2: Scénario actif (1 = Prudent, 2 = Base, 3 = Optimiste) | B2: 2
A3: Nom du scénario | B3: =CHOOSE(B2,"Prudent","Base","Optimiste") -> Base
A5: 1 · REVENUS — PRESTATIONS (Tairo Ampio, cœur du modèle — commission prélevée sur le prestataire)
A6: Libellé | B6: Valeur base | C6: Unité | D6: Valeur scénario | E6: Note
A7: Prestations demandées au mois 1 | B7: 75 | C7: prestations/mois | D7: =B7*Scenarios!$E$4 -> 75 | E7: Demande brute. Les prestations réalisées = MIN(demande, capacité de l'offre) — voir section 10.
A8: Panier moyen d'une prestation (année 1) | B8: 35000 | C8: Ar | D8: =B8*Scenarios!$E$6 -> 35000 | E8: Indexé chaque année sur l'inflation des coûts variables (section 6).
A9: Part du GMV — catégories à 10 % (Plomberie, Ménage, BTP…) | B9: 0.7 | C9: % GMV | D9: =B9 -> 0.7
A10: Part du GMV — catégories à 15 % (Cuisine) | B10: 0.1 | C10: % GMV | D10: =B10 -> 0.1
A11: Part du GMV — catégories à 20 % (Déménagement) | B11: 0.05 | C11: % GMV | D11: =B11 -> 0.05
A12: Part du GMV — catégories à 25 % (Informatique, Transport…) | B12: 0.15 | C12: % GMV | D12: =B12 -> 0.15
A13: Take rate moyen services (calculé) | C13: % | D13: =0.1*$D$9+0.15*$D$10+0.2*$D$11+0.25*$D$12 -> 0.1325
A14: Contrôle mix (doit = 100 %) | C14: % | D14: =$D$9+$D$10+$D$11+$D$12 -> 1
A16: 2 · REVENUS — ABONNEMENT Ampio+ (fusionné avec l'offre : part des prestataires actifs abonnés)
A17: Libellé | B17: Valeur base | C17: Unité | D17: Valeur scénario | E17: Note
A18: Prix de l'abonnement mensuel (année 1) | B18: 24000 | C18: Ar/mois | D18: =B18 -> 24000 | E18: Indexé chaque année (section 6).
A19: Part des prestataires actifs abonnés à Ampio+ (pénétration) | B19: 0.1 | C19: % | D19: =B19 -> 0.1 | E19: Remplace l'ancien stock d'abonnés autonome (5 abonnés, churn 6 %) : les abonnés suivent désormais le nombre de prestataires actifs (section 10).
A21: 3 · REVENUS — MISE EN LIGNE VIDÉO (Tairo Ampianaro B2B, clients professionnels)
A22: Libellé | B22: Valeur base | C22: Unité | D22: Valeur scénario | E22: Note
A23: Prix mensuel du service vidéo (année 1) | B23: 64000 | C23: Ar/mois | D23: =B23 -> 64000 | E23: Indexé chaque année (section 6).
A24: Clients vidéo actifs au mois 1 | B24: 15 | C24: clients | D24: =B24*Scenarios!$E$4 -> 15
A25: Churn mensuel clients vidéo | B25: 0.025 | C25: %/mois | D25: =MIN(1,B25*Scenarios!$E$7) -> 0.025
A27: 4 · REVENUS — LOCATION MATÉRIEL PRO (Ampindramo PRO, commission par paliers)
A28: Libellé | B28: Valeur base | C28: Unité | D28: Valeur scénario | E28: Note
A29: Locations pro demandées au mois 1 | B29: 15 | C29: locations/mois | D29: =B29*Scenarios!$E$4 -> 15
A30: Loyer total moyen d'une location pro (année 1) | B30: 15000 | C30: Ar | D30: =B30*Scenarios!$E$6 -> 15000
A31: Part du GMV — total ≤ 25 000 Ar (taux 30 %) | B31: 0.85 | C31: % GMV | D31: =B31 -> 0.85
A32: Part du GMV — 25 001 à 45 000 Ar (taux 20 %) | B32: 0.12 | C32: % GMV | D32: =B32 -> 0.12
A33: Part du GMV — > 45 000 Ar (taux 15 %) | B33: 0.03 | C33: % GMV | D33: =B33 -> 0.03
A34: Take rate moyen location pro (calculé) | C34: % | D34: =0.3*$D$31+0.2*$D$32+0.15*$D$33 -> 0.2835
A35: Contrôle mix (doit = 100 %) | C35: % | D35: =$D$31+$D$32+$D$33 -> 1
A37: 5 · REVENUS — LOCATION MATÉRIEL PARTICULIERS (Ampindramo C2C)
A38: Libellé | B38: Valeur base | C38: Unité | D38: Valeur scénario | E38: Note
A39: Locations particuliers demandées au mois 1 | B39: 12 | C39: locations/mois | D39: =B39*Scenarios!$E$4 -> 12
A40: Loyer total moyen (année 1) | B40: 10000 | C40: Ar | D40: =B40*Scenarios!$E$6 -> 10000
A41: Taux de commission particuliers (fixe, hors caution) | B41: 0.13 | C41: % | D41: =B41 -> 0.13
A43: 6 · INDEXATION DES PRIX & INFLATION (pas annuel, appliqué à chaque nouvelle année du plan)
A44: Libellé | B44: Valeur base | C44: Unité | D44: Valeur scénario | E44: Note
A45: Indexation annuelle des prix (abonnement Ampio+, service vidéo) | B45: 0.08 | C45: %/an | D45: =B45 -> 0.08 | E45: Aligné par défaut sur l'inflation des coûts pour éviter la compression silencieuse des marges.
A46: Inflation annuelle des coûts variables et des paniers / loyers moyens | B46: 0.08 | C46: %/an | D46: =B46 -> 0.08
A47: Inflation annuelle des OPEX (salaires, loyer, tech, accompagnement) | B47: 0.08 | C47: %/an | D47: =B47 -> 0.08
A49: 7 · CROISSANCE MENSUELLE DE LA DEMANDE — PAR ANNÉE, AU BUDGET D'ACQUISITION DE RÉFÉRENCE (ralentissement après A1)
A50: Segment | B50: Année 1 (base) | C50: Année 2 (base) | D50: Année 3 (base) | E50: Note | F50: Année 1 (actif) | G50: Année 2 (actif) | H50: Année 3 (actif)
A51: Clients vidéo B2B | B51: 0.05 | C51: 0.04 | D51: 0.03 | E51: Ralentissement introduit : 5 % → 4 % → 3 %. Multiplié par le facteur d'acquisition (section 9). | F51: =B51*Scenarios!$E$5 -> 0.05 | G51: =C51*Scenarios!$E$5 -> 0.04 | H51: =D51*Scenarios!$E$5 -> 0.03
A52: Prestations Ampio (demande) | B52: 0.02 | C52: 0.025 | D52: 0.02 | E52: 2 % pré-PMF, 2,5 % en A2 si collab 2 actif (sinon plafond section 8), 2 % en A3. L'accélération à 3 % a été retirée. | F52: =B52*Scenarios!$E$5 -> 0.02 | G52: =C52*Scenarios!$E$5 -> 0.025 | H52: =D52*Scenarios!$E$5 -> 0.02
A53: Locations pro (demande) | B53: 0.018 | C53: 0.025 | D53: 0.02 | E53: Même logique de plafond que les prestations tant que collab 2 absent. | F53: =B53*Scenarios!$E$5 -> 0.018 | G53: =C53*Scenarios!$E$5 -> 0.025 | H53: =D53*Scenarios!$E$5 -> 0.02
A54: Locations particuliers C2C (demande) | B54: 0.015 | C54: 0.012 | D54: 0.01 | E54: C2C plus lent (confiance, caution, concurrence WhatsApp/Facebook). Pas de bonus d'embauche. | F54: =B54*Scenarios!$E$5 -> 0.015 | G54: =C54*Scenarios!$E$5 -> 0.012 | H54: =D54*Scenarios!$E$5 -> 0.01
A56: 8 · PLAFOND DE CROISSANCE SI COLLAB 2 ABSENT (années 2–3)
A57: Libellé | B57: Valeur base | C57: Unité | D57: Valeur scénario | E57: Note
A58: Prestations Ampio — MoM tant que collab 2 inactif | B58: 0.02 | C58: %/mois | D58: =B58*Scenarios!$E$5 -> 0.02 | E58: Sans 3e personne, l'onboarding n'accélère pas. C2C non plafonné.
A59: Locations pro — MoM tant que collab 2 inactif | B59: 0.018 | C59: %/mois | D59: =B59*Scenarios!$E$5 -> 0.018
A61: 9 · ACQUISITION — BUDGET PUBLICITÉ PAR ANNÉE ET LIEN AVEC LA CROISSANCE (élasticité)
A62: Libellé | B62: Valeur base | C62: Unité | D62: Valeur scénario | E62: Note
A63: Budget publicité / acquisition — année 1 | B63: 400000 | C63: Ar/mois | D63: =B63 -> 400000 | E63: Remplace la règle « 6 % du CA » et le plancher cold-start. Saisi par année, non indexé.
A64: Budget publicité / acquisition — année 2 | B64: 500000 | C64: Ar/mois | D64: =B64 -> 500000
A65: Budget publicité / acquisition — année 3 | B65: 600000 | C65: Ar/mois | D65: =B65 -> 600000
A66: Budget de référence (celui auquel la table de croissance section 7 est calibrée) | B66: 400000 | C66: Ar/mois | D66: =B66 -> 400000
A67: Élasticité de la croissance au budget (croissance × (budget M-1 / référence)^élasticité) | B67: 0.5 | C67: coef. | D67: =B67 -> 0.5 | E67: 0,5 = rendements décroissants : doubler le budget augmente la croissance de 41 %. Budget du mois précédent (pas de circularité).
A68: Borne basse du multiplicateur de croissance | B68: 0.5 | C68: coef. | D68: =B68 -> 0.5
A69: Borne haute du multiplicateur de croissance | B69: 1.5 | C69: coef. | D69: =B69 -> 1.5
A70: Part de l'accompagnement marketing (OPEX) dédiée à l'acquisition (CAC) | B70: 0.8 | C70: % | D70: =B70 -> 0.8
A71: Part du temps fondateur dédié à l'acquisition (valorisée dans le CAC) | B71: 0.3 | C71: % | D71: =B71 -> 0.3
A72: Part des transactions réalisées issues de nouveaux clients (demande) | B72: 0.15 | C72: % | D72: =B72 -> 0.15 | E72: Hypothèse à valider avec les données d'usage.
A73: Nombre moyen de transactions par nouveau client (par mois) | B73: 1 | C73: transactions/client/mois | D73: =B73 -> 1
A74: Durée de vie moyenne d'un client transactionnel (mois) | B74: 2 | C74: mois | D74: =B74 -> 2 | E74: Clients ponctuels de la marketplace, moins engagés qu'un abonnement.
A75: Part du budget d'acquisition allouée à la DEMANDE | B75: 0.7 | C75: % | D75: =B75 -> 0.7
A76: Part du budget d'acquisition allouée à l'OFFRE | B76: 0.3 | C76: % | D76: =B76 -> 0.3 | E76: Standard marketplace : acquérir la demande coûte plus cher.
A77: Contrôle split (doit = 100 %) | C77: % | D77: =$D$75+$D$76 -> 1
A79: 10 · OFFRE — PRESTATAIRES, LOUEURS, ANNONCES (onboarding, churn, capacité CONTRAIGNANTE)
A80: Libellé | B80: Valeur base | C80: Unité | D80: Valeur scénario | E80: Note
A81: Prestataires Ampio actifs au mois 1 | B81: 25 | C81: prestataires | D81: =B81*Scenarios!$E$4 -> 25
A82: Prestataires onboardés par mois — sans collab 2 | B82: 3 | C82: prestataires/mois | D82: =B82*Scenarios!$E$5 -> 3 | E82: Capacité d'onboarding du fondateur + collab 1.
A83: Prestataires onboardés par mois — avec collab 2 | B83: 8 | C83: prestataires/mois | D83: =B83*Scenarios!$E$5 -> 8 | E83: Le collab 2 est dédié au support / onboarding.
A84: Churn mensuel des prestataires | B84: 0.03 | C84: %/mois | D84: =MIN(1,B84*Scenarios!$E$7) -> 0.03
A85: Prestations max par prestataire et par mois | B85: 8 | C85: jobs/pers/mois | D85: =B85 -> 8
A86: Loueurs pro actifs au mois 1 | B86: 8 | C86: loueurs | D86: =B86*Scenarios!$E$4 -> 8
A87: Loueurs pro onboardés par mois — sans collab 2 | B87: 1 | C87: loueurs/mois | D87: =B87*Scenarios!$E$5 -> 1
A88: Loueurs pro onboardés par mois — avec collab 2 | B88: 2 | C88: loueurs/mois | D88: =B88*Scenarios!$E$5 -> 2
A89: Churn mensuel des loueurs pro | B89: 0.02 | C89: %/mois | D89: =MIN(1,B89*Scenarios!$E$7) -> 0.02
A90: Locations max par loueur et par mois | B90: 4 | C90: loc/mois | D90: =B90 -> 4
A91: Annonces C2C actives au mois 1 | B91: 15 | C91: annonces | D91: =B91*Scenarios!$E$4 -> 15
A92: Nouvelles annonces C2C par mois | B92: 2 | C92: annonces/mois | D92: =B92*Scenarios!$E$5 -> 2 | E92: Non lié au collab 2 (peu d'onboarding).
A93: Churn mensuel des annonces C2C | B93: 0.05 | C93: %/mois | D93: =MIN(1,B93*Scenarios!$E$7) -> 0.05
A94: Locations max par annonce et par mois | B94: 1 | C94: loc/mois | D94: =B94 -> 1
A95: Taux d'utilisation maximal de la capacité (fill rate max) | B95: 0.8 | C95: % | D95: =B95 -> 0.8 | E95: Volumes réalisés = MIN(demande, offre × max × fill max). Remplace la rampe de fill rate saisie et les KPI de liquidité tautologiques.
A97: 11 · LANCEMENT (M1–M6) — subvention d'offre sur les prestations
A98: Libellé | B98: Valeur base | C98: Unité | D98: Valeur scénario | E98: Note
A99: Durée de la phase de lancement | B99: 6 | C99: mois | D99: =B99 -> 6
A100: Réduction du take rate Ampio pendant le lancement | B100: 0.02 | C100: % (0,02 = 2 points) | D100: =B100 -> 0.02 | E100: Corrigé : était saisi « 2 » (200 points), ce qui annulait tout le CA commissions M1–M6. Mix 13,25 % → 11,25 %.
A102: 12 · COÛTS VARIABLES — COGS ET COÛTS OPÉRATIONNELS LIÉS AU VOLUME
A103: Libellé | B103: Valeur base | C103: Unité | D103: Valeur scénario | E103: Note
A104: SMS de notification (2 × 35,71 Ar) — prestations Ampio + locations C2C | B104: 71.42 | C104: Ar/transaction | D104: =B104 -> 71.42
A105: Commission Mobile Money par transaction | B105: 0.03 | C105: % | D105: =B105 -> 0.03 | E105: 3 % du montant brut : CA abonnements Ampio+, GMV prestations, GMV locations pro et C2C. Exclut le service vidéo (paiement B2B).
A106: Support / modération par transaction (Ampio + loc pro + C2C) | B106: 1000 | C106: Ar/transaction | D106: =B106*Scenarios!$E$8*(1+IF($B$158=1,$B$161,0)) -> 1000
A107: Vérification / onboarding d'un nouveau client (prestataire, loueur, client vidéo, client demande) | B107: 3000 | C107: Ar/nouveau | D107: =B107*Scenarios!$E$8*(1+IF($B$158=1,$B$161,0)) -> 3000
A108: Provision remboursements / litiges | B108: 0.01 | C108: % du GMV | D108: =B108*Scenarios!$E$8*(1+IF($B$158=1,$B$161,0)) -> 0.01
A110: 13 · OPEX MENSUEL (charges fixes, année 1)
A111: Libellé | B111: Valeur base | C111: Unité | D111: Valeur scénario | E111: Note
A112: Loyer et domiciliation | B112: 125000 | C112: Ar/mois | D112: =B112*Scenarios!$E$8*(1+IF($B$158=1,$B$161,0)) -> 125000 | E112: Wezara
A113: Salaire brut fondateur | B113: 800000 | C113: Ar/mois | D113: =B113*Scenarios!$E$8*(1+IF($B$158=1,$B$161,0)) -> 800000
...

Sheet Scenarios
A1: SCÉNARIOS — multiplicateurs appliqués aux paramètres de base
A2: Le scénario actif se choisit dans Parametres!B2. Colonne « Actif » = multiplicateur appliqué.
A3: Multiplicateur | B3: Prudent (P10) | C3: Base (P50) | D3: Optimiste (P90) | E3: Actif
A4: Volumes de départ (clients, transactions) | B4: 0.7 | C4: 1 | D4: 1.3 | E4: =INDEX(B4:D4,1,Parametres!$B$2) -> 1
A5: Croissance mensuelle | B5: 0.7 | C5: 1 | D5: 1.3 | E5: =INDEX(B5:D5,1,Parametres!$B$2) -> 1
A6: Paniers moyens / prix transactionnels | B6: 0.9 | C6: 1 | D6: 1.1 | E6: =INDEX(B6:D6,1,Parametres!$B$2) -> 1
A7: Churn (attrition) | B7: 1.3 | C7: 1 | D7: 0.8 | E7: =INDEX(B7:D7,1,Parametres!$B$2) -> 1
A8: OPEX (charges fixes) | B8: 1.05 | C8: 1 | D8: 1 | E8: =INDEX(B8:D8,1,Parametres!$B$2) -> 1
A10: Note : pour comparer les scénarios, changer Parametres!B2 (1/2/3) — tout le classeur (Plan ventes, P&L, Trésorerie, KPI, Dashboard) se recalcule automatiquement.

Sheet Plan ventes
A1: PLAN DE VENTES — acquisition, offre (capacité contraignante), demande, GMV, CA (M1–M36) + flag embauche
A2: Année | B2: =INT((B3-1)/12)+1 -> 1 | C2: =INT((C3-1)/12)+1 -> 1 | D2: =INT((D3-1)/12)+1 -> 1 | E2: =INT((E3-1)/12)+1 -> 1 | F2: =INT((F3-1)/12)+1 -> 1 | G2: =INT((G3-1)/12)+1 -> 1 | H2: =INT((H3-1)/12)+1 -> 1 | I2: =INT((I3-1)/12)+1 -> 1 | ... AK2: =INT((AK3-1)/12)+1 -> 3
A3: Mois | B3: 1 | C3: 2 | D3: 3 | E3: 4 | F3: 5 | G3: 6 | H3: 7 | I3: 8 | J3: 9 | K3: 10 | L3: 11 | M3: 12 | N3: 13 | O3: 14 | P3: 15 | Q3: 16 | R3: 17 | S3: 18 | T3: 19 | U3: 20 | V3: 21 | W3: 22 | X3: 23 | Y3: 24 | Z3: 25 | AA3: 26 | AB3: 27 | AC3: 28 | AD3: 29 | AE3: 30 | AF3: 31 | AG3: 32 | AH3: 33 | AI3: 34 | AJ3: 35 | AK3: 36
A5: ACQUISITION → CROISSANCE
A6: Budget publicité / acquisition du mois (Ar, saisi par année — section 9) | B6: =CHOOSE(B$2,Parametres!$D$63,Parametres!$D$64,Parametres!$D$65) -> 400000 | C6: =CHOOSE(C$2,Parametres!$D$63,Parametres!$D$64,Parametres!$D$65) -> 400000 | D6: =CHOOSE(D$2,Parametres!$D$63,Parametres!$D$64,Parametres!$D$65) -> 400000 | E6: =CHOOSE(E$2,Parametres!$D$63,Parametres!$D$64,Parametres!$D$65) -> 400000 | F6: =CHOOSE(F$2,Parametres!$D$63,Parametres!$D$64,Parametres!$D$65) -> 400000 | G6: =CHOOSE(G$2,Parametres!$D$63,Parametres!$D$64,Parametres!$D$65) -> 400000 | H6: =CHOOSE(H$2,Parametres!$D$63,Parametres!$D$64,Parametres!$D$65) -> 400000 | I6: =CHOOSE(I$2,Parametres!$D$63,Parametres!$D$64,Parametres!$D$65) -> 400000 | ... AK6: =CHOOSE(AK$2,Parametres!$D$63,Parametres!$D$64,Parametres!$D$65) -> 600000
A7: Multiplicateur de croissance lié au budget (élasticité, budget du mois précédent, borné) | B7: =1 -> 1 | C7: =MIN(Parametres!$D$69,MAX(Parametres!$D$68,IF(Parametres!$D$66=0,1,(B6/Parametres!$D$66)^Parametres!$D$67))) -> 1 | D7: =MIN(Parametres!$D$69,MAX(Parametres!$D$68,IF(Parametres!$D$66=0,1,(C6/Parametres!$D$66)^Parametres!$D$67))) -> 1 | E7: =MIN(Parametres!$D$69,MAX(Parametres!$D$68,IF(Parametres!$D$66=0,1,(D6/Parametres!$D$66)^Parametres!$D$67))) -> 1 | F7: =MIN(Parametres!$D$69,MAX(Parametres!$D$68,IF(Parametres!$D$66=0,1,(E6/Parametres!$D$66)^Parametres!$D$67))) -> 1 | G7: =MIN(Parametres!$D$69,MAX(Parametres!$D$68,IF(Parametres!$D$66=0,1,(F6/Parametres!$D$66)^Parametres!$D$67))) -> 1 | H7: =MIN(Parametres!$D$69,MAX(Parametres!$D$68,IF(Parametres!$D$66=0,1,(G6/Parametres!$D$66)^Parametres!$D$67))) -> 1 | I7: =MIN(Parametres!$D$69,MAX(Parametres!$D$68,IF(Parametres!$D$66=0,1,(H6/Parametres!$D$66)^Parametres!$D$67))) -> 1 | J7: =MIN(Parametres!$D$69,MAX(Parametres!$D$68,IF(Parametres!$D$66=0,1,(I6/Parametres!$D$66)^Parametres!$D$67))) -> 1 | ... AK7: =MIN(Parametres!$D$69,MAX(Parametres!$D$68,IF(Parametres!$D$66=0,1,(AJ6/Parametres!$D$66)^Parametres!$D$67))) -> 1.2247449
A8: Croissance gelée (stress test : retard de lancement) — 1 = oui | B8: =IF(AND(Parametres!$B$158=1,B$3<=Parametres!$B$160),1,0) -> 0 | C8: =IF(AND(Parametres!$B$158=1,C$3<=Parametres!$B$160),1,0) -> 0 | D8: =IF(AND(Parametres!$B$158=1,D$3<=Parametres!$B$160),1,0) -> 0 | E8: =IF(AND(Parametres!$B$158=1,E$3<=Parametres!$B$160),1,0) -> 0 | F8: =IF(AND(Parametres!$B$158=1,F$3<=Parametres!$B$160),1,0) -> 0 | G8: =IF(AND(Parametres!$B$158=1,G$3<=Parametres!$B$160),1,0) -> 0 | H8: =IF(AND(Parametres!$B$158=1,H$3<=Parametres!$B$160),1,0) -> 0 | I8: =IF(AND(Parametres!$B$158=1,I$3<=Parametres!$B$160),1,0) -> 0 | ... AK8: =IF(AND(Parametres!$B$158=1,AK$3<=Parametres!$B$160),1,0) -> 0
A10: OFFRE & DEMANDE — PRESTATIONS AMPIO (prestataires, capacité, GMV, commissions, abonnements Ampio+)
A11: Nouveaux prestataires onboardés (M1 = stock initial) | B11: =Parametres!$D$81*(1-IF(Parametres!$B$158=1,Parametres!$B$159,0)) -> 25 | C11: =IF(B70=1,Parametres!$D$83,Parametres!$D$82) -> 3 | D11: =IF(C70=1,Parametres!$D$83,Parametres!$D$82) -> 3 | E11: =IF(D70=1,Parametres!$D$83,Parametres!$D$82) -> 3 | F11: =IF(E70=1,Parametres!$D$83,Parametres!$D$82) -> 3 | G11: =IF(F70=1,Parametres!$D$83,Parametres!$D$82) -> 3 | H11: =IF(G70=1,Parametres!$D$83,Parametres!$D$82) -> 3 | I11: =IF(H70=1,Parametres!$D$83,Parametres!$D$82) -> 3 | J11: =IF(I70=1,Parametres!$D$83,Parametres!$D$82) -> 3 | ... AK11: =IF(AJ70=1,Parametres!$D$83,Parametres!$D$82) -> 8
A12: Prestataires perdus (churn) | B12: =0 -> 0 | C12: =B13*Parametres!$D$84 -> 0.75 | D12: =C13*Parametres!$D$84 -> 0.8175 | E12: =D13*Parametres!$D$84 -> 0.882975 | F12: =E13*Parametres!$D$84 -> 0.94648575 | G12: =F13*Parametres!$D$84 -> 1.0080912 | H12: =G13*Parametres!$D$84 -> 1.0678484 | I12: =H13*Parametres!$D$84 -> 1.125813 | J12: =I13*Parametres!$D$84 -> 1.1820386 | ... AK12: =AJ13*Parametres!$D$84 -> 3.5141098
A13: Prestataires actifs (stock × (1 − churn) + nouveaux) | B13: =B11 -> 25 | C13: =B13*(1-Parametres!$D$84)+C11 -> 27.25 | D13: =C13*(1-Parametres!$D$84)+D11 -> 29.4325 | E13: =D13*(1-Parametres!$D$84)+E11 -> 31.549525 | F13: =E13*(1-Parametres!$D$84)+F11 -> 33.603039 | G13: =F13*(1-Parametres!$D$84)+G11 -> 35.594948 | H13: =G13*(1-Parametres!$D$84)+H11 -> 37.5271 | I13: =H13*(1-Parametres!$D$84)+I11 -> 39.401287 | J13: =I13*(1-Parametres!$D$84)+J11 -> 41.219248 | ... AK13: =AJ13*(1-Parametres!$D$84)+AK11 -> 121.62289
A14: Capacité mensuelle (actifs × max par mois × fill rate max) | B14: =B13*Parametres!$D$85*Parametres!$D$95 -> 160 | C14: =C13*Parametres!$D$85*Parametres!$D$95 -> 174.4 | D14: =D13*Parametres!$D$85*Parametres!$D$95 -> 188.368 | E14: =E13*Parametres!$D$85*Parametres!$D$95 -> 201.91696 | F14: =F13*Parametres!$D$85*Parametres!$D$95 -> 215.05945 | G14: =G13*Parametres!$D$85*Parametres!$D$95 -> 227.80767 | H14: =H13*Parametres!$D$85*Parametres!$D$95 -> 240.17344 | I14: =I13*Parametres!$D$85*Parametres!$D$95 -> 252.16823 | ... AK14: =AK13*Parametres!$D$85*Parametres!$D$95 -> 778.38646
A15: Abonnés Ampio+ (pénétration × prestataires actifs) | B15: =B13*Parametres!$D$19 -> 2.5 | C15: =C13*Parametres!$D$19 -> 2.725 | D15: =D13*Parametres!$D$19 -> 2.94325 | E15: =E13*Parametres!$D$19 -> 3.1549525 | F15: =F13*Parametres!$D$19 -> 3.3603039 | G15: =G13*Parametres!$D$19 -> 3.5594948 | H15: =H13*Parametres!$D$19 -> 3.75271 | I15: =I13*Parametres!$D$19 -> 3.9401287 | ... AK15: =AK13*Parametres!$D$19 -> 12.162289
A16: Prix de l'abonnement indexé | B16: =Parametres!$D$18*(1+Parametres!$D$45)^(B$2-1) -> 24000 | C16: =Parametres!$D$18*(1+Parametres!$D$45)^(C$2-1) -> 24000 | D16: =Parametres!$D$18*(1+Parametres!$D$45)^(D$2-1) -> 24000 | E16: =Parametres!$D$18*(1+Parametres!$D$45)^(E$2-1) -> 24000 | F16: =Parametres!$D$18*(1+Parametres!$D$45)^(F$2-1) -> 24000 | G16: =Parametres!$D$18*(1+Parametres!$D$45)^(G$2-1) -> 24000 | H16: =Parametres!$D$18*(1+Parametres!$D$45)^(H$2-1) -> 24000 | I16: =Parametres!$D$18*(1+Parametres!$D$45)^(I$2-1) -> 24000 | ... AK16: =Parametres!$D$18*(1+Parametres!$D$45)^(AK$2-1) -> 27993.6
A17: CA abonnements Ampio+ (MRR) | B17: =B15*B16 -> 60000 | C17: =C15*C16 -> 65400 | D17: =D15*D16 -> 70638 | E17: =E15*E16 -> 75718.86 | F17: =F15*F16 -> 80647.294 | G17: =G15*G16 -> 85427.875 | H17: =H15*H16 -> 90065.039 | I17: =I15*I16 -> 94563.088 | ... AK17: =AK15*AK16 -> 340466.24
A18: Demande (prestations) — croissance section 7 × multiplicateur acquisition | B18: =Parametres!$D$7*(1-IF(Parametres!$B$158=1,Parametres!$B$159,0)) -> 75 | C18: =B18*(1+IF(C8=1,0,IF(AND(C$2>=2,B70=0),Parametres!$D$58,CHOOSE(C$2,Parametres!$F$52,Parametres!$G$52,Parametres!$H$52))*C7)) -> 76.5 | D18: =C18*(1+IF(D8=1,0,IF(AND(D$2>=2,C70=0),Parametres!$D$58,CHOOSE(D$2,Parametres!$F$52,Parametres!$G$52,Parametres!$H$52))*D7)) -> 78.03 | E18: =D18*(1+IF(E8=1,0,IF(AND(E$2>=2,D70=0),Parametres!$D$58,CHOOSE(E$2,Parametres!$F$52,Parametres!$G$52,Parametres!$H$52))*E7)) -> 79.5906 | F18: =E18*(1+IF(F8=1,0,IF(AND(F$2>=2,E70=0),Parametres!$D$58,CHOOSE(F$2,Parametres!$F$52,Parametres!$G$52,Parametres!$H$52))*F7)) -> 81.182412 | G18: =F18*(1+IF(G8=1,0,IF(AND(G$2>=2,F70=0),Parametres!$D$58,CHOOSE(G$2,Parametres!$F$52,Parametres!$G$52,Parametres!$H$52))*G7)) -> 82.80606 | H18: =G18*(1+IF(H8=1,0,IF(AND(H$2>=2,G70=0),Parametres!$D$58,CHOOSE(H$2,Parametres!$F$52,Parametres!$G$52,Parametres!$H$52))*H7)) -> 84.462181 | I18: =H18*(1+IF(I8=1,0,IF(AND(I$2>=2,H70=0),Parametres!$D$58,CHOOSE(I$2,Parametres!$F$52,Parametres!$G$52,Parametres!$H$52))*I7)) -> 86.151425 | J18: =I18*(1+IF(J8=1,0,IF(AND(J$2>=2,I70=0),Parametres!$D$58,CHOOSE(J$2,Parametres!$F$52,Parametres!$G$52,Parametres!$H$52))*J7)) -> 87.874454 | ... AK18: =AJ18*(1+IF(AK8=1,0,IF(AND(AK$2>=2,AJ70=0),Parametres!$D$58,CHOOSE(AK$2,Parametres!$F$52,Parametres!$G$52,Parametres!$H$52))*AK7)) -> 161.85301
A19: Prestations réalisées = MIN(demande, capacité) | B19: =MIN(B18,B14) -> 75 | C19: =MIN(C18,C14) -> 76.5 | D19: =MIN(D18,D14) -> 78.03 | E19: =MIN(E18,E14) -> 79.5906 | F19: =MIN(F18,F14) -> 81.182412 | G19: =MIN(G18,G14) -> 82.80606 | H19: =MIN(H18,H14) -> 84.462181 | I19: =MIN(I18,I14) -> 86.151425 | ... AK19: =MIN(AK18,AK14) -> 161.85301
A20: Demande non servie (pénurie d'offre) | B20: =B18-B19 -> 0 | C20: =C18-C19 -> 0 | D20: =D18-D19 -> 0 | E20: =E18-E19 -> 0 | F20: =F18-F19 -> 0 | G20: =G18-G19 -> 0 | H20: =H18-H19 -> 0 | I20: =I18-I19 -> 0 | ... AK20: =AK18-AK19 -> 0
A21: Taux d'utilisation de la capacité brute (réalisées / (actifs × max)) | B21: =IF(B13*Parametres!$D$85=0,0,B19/(B13*Parametres!$D$85)) -> 0.375 | C21: =IF(C13*Parametres!$D$85=0,0,C19/(C13*Parametres!$D$85)) -> 0.35091743 | D21: =IF(D13*Parametres!$D$85=0,0,D19/(D13*Parametres!$D$85)) -> 0.33139387 | E21: =IF(E13*Parametres!$D$85=0,0,E19/(E13*Parametres!$D$85)) -> 0.31533993 | F21: =IF(F13*Parametres!$D$85=0,0,F19/(F13*Parametres!$D$85)) -> 0.30199059 | G21: =IF(G13*Parametres!$D$85=0,0,G19/(G13*Parametres!$D$85)) -> 0.29079288 | H21: =IF(H13*Parametres!$D$85=0,0,H19/(H13*Parametres!$D$85)) -> 0.28133729 | I21: =IF(I13*Parametres!$D$85=0,0,I19/(I13*Parametres!$D$85)) -> 0.27331412 | ... AK21: =IF(AK13*Parametres!$D$85=0,0,AK19/(AK13*Parametres!$D$85)) -> 0.1663472
A22: Panier / loyer moyen (indexé par an) | B22: =Parametres!$D$8*(1+Parametres!$D$46)^(B$2-1) -> 35000 | C22: =Parametres!$D$8*(1+Parametres!$D$46)^(C$2-1) -> 35000 | D22: =Parametres!$D$8*(1+Parametres!$D$46)^(D$2-1) -> 35000 | E22: =Parametres!$D$8*(1+Parametres!$D$46)^(E$2-1) -> 35000 | F22: =Parametres!$D$8*(1+Parametres!$D$46)^(F$2-1) -> 35000 | G22: =Parametres!$D$8*(1+Parametres!$D$46)^(G$2-1) -> 35000 | H22: =Parametres!$D$8*(1+Parametres!$D$46)^(H$2-1) -> 35000 | I22: =Parametres!$D$8*(1+Parametres!$D$46)^(I$2-1) -> 35000 | ... AK22: =Parametres!$D$8*(1+Parametres!$D$46)^(AK$2-1) -> 40824
A23: GMV prestations | B23: =B19*B22 -> 2625000 | C23: =C19*C22 -> 2677500 | D23: =D19*D22 -> 2731050 | E23: =E19*E22 -> 2785671 | F23: =F19*F22 -> 2841384.4 | G23: =G19*G22 -> 2898212.1 | H23: =H19*H22 -> 2956176.4 | I23: =I19*I22 -> 3015299.9 | ... AK23: =AK19*AK22 -> 6607487.2
A24: CA commissions prestations (take rate mix − subvention de lancement M1–M6) | B24: =MAX(0,B23*(Parametres!$D$13-IF(B$3<=Parametres!$D$99,Parametres!$D$100,0))) -> 295312.5 | C24: =MAX(0,C23*(Parametres!$D$13-IF(C$3<=Parametres!$D$99,Parametres!$D$100,0))) -> 301218.75 | D24: =MAX(0,D23*(Parametres!$D$13-IF(D$3<=Parametres!$D$99,Parametres!$D$100,0))) -> 307243.12 | E24: =MAX(0,E23*(Parametres!$D$13-IF(E$3<=Parametres!$D$99,Parametres!$D$100,0))) -> 313387.99 | F24: =MAX(0,F23*(Parametres!$D$13-IF(F$3<=Parametres!$D$99,Parametres!$D$100,0))) -> 319655.75 | G24: =MAX(0,G23*(Parametres!$D$13-IF(G$3<=Parametres!$D$99,Parametres!$D$100,0))) -> 326048.86 | H24: =MAX(0,H23*(Parametres!$D$13-IF(H$3<=Parametres!$D$99,Parametres!$D$100,0))) -> 391693.37 | I24: =MAX(0,I23*(Parametres!$D$13-IF(I$3<=Parametres!$D$99,Parametres!$D$100,0))) -> 399527.23 | ... AK24: =MAX(0,AK23*(Parametres!$D$13-IF(AK$3<=Parametres!$D$99,Parametres!$D$100,0))) -> 875492.06
A26: MISE EN LIGNE VIDÉO — Ampianaro B2B (croissance ralentie A2/A3 × multiplicateur acquisition)
A27: Nouveaux clients vidéo (croissance nette + remplacement du churn) | B27: =B29 -> 15 | C27: =C29-B29*(1-Parametres!$D$25) -> 1.125 | D27: =D29-C29*(1-Parametres!$D$25) -> 1.18125 | E27: =E29-D29*(1-Parametres!$D$25) -> 1.2403125 | F27: =F29-E29*(1-Parametres!$D$25) -> 1.3023281 | G27: =G29-F29*(1-Parametres!$D$25) -> 1.3674445 | H27: =H29-G29*(1-Parametres!$D$25) -> 1.4358168 | I27: =I29-H29*(1-Parametres!$D$25) -> 1.5076076 | J27: =J29-I29*(1-Parametres!$D$25) -> 1.582988 | ... AK27: =AK29-AJ29*(1-Parametres!$D$25) -> 3.952131
A28: Clients perdus (churn) | B28: =0 -> 0 | C28: =B29*Parametres!$D$25 -> 0.375 | D28: =C29*Parametres!$D$25 -> 0.39375 | E28: =D29*Parametres!$D$25 -> 0.4134375 | F28: =E29*Parametres!$D$25 -> 0.43410938 | G28: =F29*Parametres!$D$25 -> 0.45581484 | H28: =G29*Parametres!$D$25 -> 0.47860559 | I28: =H29*Parametres!$D$25 -> 0.50253587 | J28: =I29*Parametres!$D$25 -> 0.52766266 | ... AK28: =AJ29*Parametres!$D$25 -> 1.6002514
A29: Clients vidéo actifs | B29: =Parametres!$D$24*(1-IF(Parametres!$B$158=1,Parametres!$B$159,0)) -> 15 | C29: =B29*(1+IF(C8=1,0,CHOOSE(C$2,Parametres!$F$51,Parametres!$G$51,Parametres!$H$51)*C7)) -> 15.75 | D29: =C29*(1+IF(D8=1,0,CHOOSE(D$2,Parametres!$F$51,Parametres!$G$51,Parametres!$H$51)*D7)) -> 16.5375 | E29: =D29*(1+IF(E8=1,0,CHOOSE(E$2,Parametres!$F$51,Parametres!$G$51,Parametres!$H$51)*E7)) -> 17.364375 | F29: =E29*(1+IF(F8=1,0,CHOOSE(F$2,Parametres!$F$51,Parametres!$G$51,Parametres!$H$51)*F7)) -> 18.232594 | G29: =F29*(1+IF(G8=1,0,CHOOSE(G$2,Parametres!$F$51,Parametres!$G$51,Parametres!$H$51)*G7)) -> 19.144223 | H29: =G29*(1+IF(H8=1,0,CHOOSE(H$2,Parametres!$F$51,Parametres!$G$51,Parametres!$H$51)*H7)) -> 20.101435 | I29: =H29*(1+IF(I8=1,0,CHOOSE(I$2,Parametres!$F$51,Parametres!$G$51,Parametres!$H$51)*I7)) -> 21.106506 | J29: =I29*(1+IF(J8=1,0,CHOOSE(J$2,Parametres!$F$51,Parametres!$G$51,Parametres!$H$51)*J7)) -> 22.161832 | ... AK29: =AJ29*(1+IF(AK8=1,0,CHOOSE(AK$2,Parametres!$F$51,Parametres!$G$51,Parametres!$H$51)*AK7)) -> 66.361934
A30: Prix du service vidéo indexé | B30: =Parametres!$D$23*(1+Parametres!$D$45)^(B$2-1) -> 64000 | C30: =Parametres!$D$23*(1+Parametres!$D$45)^(C$2-1) -> 64000 | D30: =Parametres!$D$23*(1+Parametres!$D$45)^(D$2-1) -> 64000 | E30: =Parametres!$D$23*(1+Parametres!$D$45)^(E$2-1) -> 64000 | F30: =Parametres!$D$23*(1+Parametres!$D$45)^(F$2-1) -> 64000 | G30: =Parametres!$D$23*(1+Parametres!$D$45)^(G$2-1) -> 64000 | H30: =Parametres!$D$23*(1+Parametres!$D$45)^(H$2-1) -> 64000 | I30: =Parametres!$D$23*(1+Parametres!$D$45)^(I$2-1) -> 64000 | ... AK30: =Parametres!$D$23*(1+Parametres!$D$45)^(AK$2-1) -> 74649.6
A31: CA vidéo (MRR Ampianaro B2B) | B31: =B29*B30 -> 960000 | C31: =C29*C30 -> 1008000 | D31: =D29*D30 -> 1058400 | E31: =E29*E30 -> 1111320 | F31: =F29*F30 -> 1166886 | G31: =G29*G30 -> 1225230.3 | H31: =H29*H30 -> 1286491.8 | I31: =I29*I30 -> 1350816.4 | ... AK31: =AK29*AK30 -> 4953891.9
A33: OFFRE & DEMANDE — LOCATIONS PRO Ampindramo B2B2C (loueurs, capacité, paliers 30/20/15 %)
A34: Nouveaux loueurs pro onboardés (M1 = stock initial) | B34: =Parametres!$D$86*(1-IF(Parametres!$B$158=1,Parametres!$B$159,0)) -> 8 | C34: =IF(B70=1,Parametres!$D$88,Parametres!$D$87) -> 1 | D34: =IF(C70=1,Parametres!$D$88,Parametres!$D$87) -> 1 | E34: =IF(D70=1,Parametres!$D$88,Parametres!$D$87) -> 1 | F34: =IF(E70=1,Parametres!$D$88,Parametres!$D$87) -> 1 | G34: =IF(F70=1,Parametres!$D$88,Parametres!$D$87) -> 1 | H34: =IF(G70=1,Parametres!$D$88,Parametres!$D$87) -> 1 | I34: =IF(H70=1,Parametres!$D$88,Parametres!$D$87) -> 1 | J34: =IF(I70=1,Parametres!$D$88,Parametres!$D$87) -> 1 | ... AK34: =IF(AJ70=1,Parametres!$D$88,Parametres!$D$87) -> 2
A35: Loueurs pro perdus (churn) | B35: =0 -> 0 | C35: =B36*Parametres!$D$89 -> 0.16 | D35: =C36*Parametres!$D$89 -> 0.1768 | E35: =D36*Parametres!$D$89 -> 0.193264 | F35: =E36*Parametres!$D$89 -> 0.20939872 | G35: =F36*Parametres!$D$89 -> 0.22521075 | H35: =G36*Parametres!$D$89 -> 0.24070653 | I35: =H36*Parametres!$D$89 -> 0.2558924 | J35: =I36*Parametres!$D$89 -> 0.27077455 | ... AK35: =AJ36*Parametres!$D$89 -> 0.7602918
A36: Loueurs pro actifs (stock × (1 − churn) + nouveaux) | B36: =B34 -> 8 | C36: =B36*(1-Parametres!$D$89)+C34 -> 8.84 | D36: =C36*(1-Parametres!$D$89)+D34 -> 9.6632 | E36: =D36*(1-Parametres!$D$89)+E34 -> 10.469936 | F36: =E36*(1-Parametres!$D$89)+F34 -> 11.260537 | G36: =F36*(1-Parametres!$D$89)+G34 -> 12.035327 | H36: =G36*(1-Parametres!$D$89)+H34 -> 12.79462 | I36: =H36*(1-Parametres!$D$89)+I34 -> 13.538728 | J36: =I36*(1-Parametres!$D$89)+J34 -> 14.267953 | ... AK36: =AJ36*(1-Parametres!$D$89)+AK34 -> 39.254298
A37: Capacité mensuelle (actifs × max par mois × fill rate max) | B37: =B36*Parametres!$D$90*Parametres!$D$95 -> 25.6 | C37: =C36*Parametres!$D$90*Parametres!$D$95 -> 28.288 | D37: =D36*Parametres!$D$90*Parametres!$D$95 -> 30.92224 | E37: =E36*Parametres!$D$90*Parametres!$D$95 -> 33.503795 | F37: =F36*Parametres!$D$90*Parametres!$D$95 -> 36.033719 | G37: =G36*Parametres!$D$90*Parametres!$D$95 -> 38.513045 | H37: =H36*Parametres!$D$90*Parametres!$D$95 -> 40.942784 | I37: =I36*Parametres!$D$90*Parametres!$D$95 -> 43.323928 | ... AK37: =AK36*Parametres!$D$90*Parametres!$D$95 -> 125.61375
A38: Demande (locations pro) — croissance section 7 × multiplicateur acquisition | B38: =Parametres!$D$29*(1-IF(Parametres!$B$158=1,Parametres!$B$159,0)) -> 15 | C38: =B38*(1+IF(C8=1,0,IF(AND(C$2>=2,B70=0),Parametres!$D$59,CHOOSE(C$2,Parametres!$F$53,Parametres!$G$53,Parametres!$H$53))*C7)) -> 15.27 | D38: =C38*(1+IF(D8=1,0,IF(AND(D$2>=2,C70=0),Parametres!$D$59,CHOOSE(D$2,Parametres!$F$53,Parametres!$G$53,Parametres!$H$53))*D7)) -> 15.54486 | E38: =D38*(1+IF(E8=1,0,IF(AND(E$2>=2,D70=0),Parametres!$D$59,CHOOSE(E$2,Parametres!$F$53,Parametres!$G$53,Parametres!$H$53))*E7)) -> 15.824667 | F38: =E38*(1+IF(F8=1,0,IF(AND(F$2>=2,E70=0),Parametres!$D$59,CHOOSE(F$2,Parametres!$F$53,Parametres!$G$53,Parametres!$H$53))*F7)) -> 16.109511 | G38: =F38*(1+IF(G8=1,0,IF(AND(G$2>=2,F70=0),Parametres!$D$59,CHOOSE(G$2,Parametres!$F$53,Parametres!$G$53,Parametres!$H$53))*G7)) -> 16.399483 | H38: =G38*(1+IF(H8=1,0,IF(AND(H$2>=2,G70=0),Parametres!$D$59,CHOOSE(H$2,Parametres!$F$53,Parametres!$G$53,Parametres!$H$53))*H7)) -> 16.694673 | I38: =H38*(1+IF(I8=1,0,IF(AND(I$2>=2,H70=0),Parametres!$D$59,CHOOSE(I$2,Parametres!$F$53,Parametres!$G$53,Parametres!$H$53))*I7)) -> 16.995178 | J38: =I38*(1+IF(J8=1,0,IF(AND(J$2>=2,I70=0),Parametres!$D$59,CHOOSE(J$2,Parametres!$F$53,Parametres!$G$53,Parametres!$H$53))*J7)) -> 17.301091 | ... AK38: =AJ38*(1+IF(AK8=1,0,IF(AND(AK$2>=2,AJ70=0),Parametres!$D$59,CHOOSE(AK$2,Parametres!$F$53,Parametres!$G$53,Parametres!$H$53))*AK7)) -> 30.79719
A39: Locations pro réalisées = MIN(demande, capacité) | B39: =MIN(B38,B37) -> 15 | C39: =MIN(C38,C37) -> 15.27 | D39: =MIN(D38,D37) -> 15.54486 | E39: =MIN(E38,E37) -> 15.824667 | F39: =MIN(F38,F37) -> 16.109511 | G39: =MIN(G38,G37) -> 16.399483 | H39: =MIN(H38,H37) -> 16.694673 | I39: =MIN(I38,I37) -> 16.995178 | ... AK39: =MIN(AK38,AK37) -> 30.79719
A40: Demande non servie (pénurie d'offre) | B40: =B38-B39 -> 0 | C40: =C38-C39 -> 0 | D40: =D38-D39 -> 0 | E40: =E38-E39 -> 0 | F40: =F38-F39 -> 0 | G40: =G38-G39 -> 0 | H40: =H38-H39 -> 0 | I40: =I38-I39 -> 0 | ... AK40: =AK38-AK39 -> 0
A41: Taux d'utilisation de la capacité brute (réalisées / (actifs × max)) | B41: =IF(B36*Parametres!$D$90=0,0,B39/(B36*Parametres!$D$90)) -> 0.46875 | C41: =IF(C36*Parametres!$D$90=0,0,C39/(C36*Parametres!$D$90)) -> 0.43184389 | D41: =IF(D36*Parametres!$D$90=0,0,D39/(D36*Parametres!$D$90)) -> 0.40216647 | E41: =IF(E36*Parametres!$D$90=0,0,E39/(E36*Parametres!$D$90)) -> 0.3778597 | F41: =IF(F36*Parametres!$D$90=0,0,F39/(F36*Parametres!$D$90)) -> 0.35765415 | G41: =IF(G36*Parametres!$D$90=0,0,G39/(G36*Parametres!$D$90)) -> 0.34065305 | H41: =IF(H36*Parametres!$D$90=0,0,H39/(H36*Parametres!$D$90)) -> 0.32620495 | I41: =IF(I36*Parametres!$D$90=0,0,I39/(I36*Parametres!$D$90)) -> 0.31382524 | ... AK41: =IF(AK36*Parametres!$D$90=0,0,AK39/(AK36*Parametres!$D$90)) -> 0.19613897
A42: Panier / loyer moyen (indexé par an) | B42: =Parametres!$D$30*(1+Parametres!$D$46)^(B$2-1) -> 15000 | C42: =Parametres!$D$30*(1+Parametres!$D$46)^(C$2-1) -> 15000 | D42: =Parametres!$D$30*(1+Parametres!$D$46)^(D$2-1) -> 15000 | E42: =Parametres!$D$30*(1+Parametres!$D$46)^(E$2-1) -> 15000 | F42: =Parametres!$D$30*(1+Parametres!$D$46)^(F$2-1) -> 15000 | G42: =Parametres!$D$30*(1+Parametres!$D$46)^(G$2-1) -> 15000 | H42: =Parametres!$D$30*(1+Parametres!$D$46)^(H$2-1) -> 15000 | I42: =Parametres!$D$30*(1+Parametres!$D$46)^(I$2-1) -> 15000 | ... AK42: =Parametres!$D$30*(1+Parametres!$D$46)^(AK$2-1) -> 17496
A43: GMV locations pro | B43: =B39*B42 -> 225000 | C43: =C39*C42 -> 229050 | D43: =D39*D42 -> 233172.9 | E43: =E39*E42 -> 237370.01 | F43: =F39*F42 -> 241642.67 | G43: =G39*G42 -> 245992.24 | H43: =H39*H42 -> 250420.1 | I43: =I39*I42 -> 254927.66 | ... AK43: =AK39*AK42 -> 538827.64
A44: CA commissions locations pro | B44: =B43*Parametres!$D$34 -> 63787.5 | C44: =C43*Parametres!$D$34 -> 64935.675 | D44: =D43*Parametres!$D$34 -> 66104.517 | E44: =E43*Parametres!$D$34 -> 67294.398 | F44: =F43*Parametres!$D$34 -> 68505.698 | G44: =G43*Parametres!$D$34 -> 69738.8 | H44: =H43*Parametres!$D$34 -> 70994.099 | I44: =I43*Parametres!$D$34 -> 72271.992 | ... AK44: =AK43*Parametres!$D$34 -> 152757.64
A46: OFFRE & DEMANDE — LOCATIONS PARTICULIERS Ampindramo C2C (annonces, capacité, 13 %)
A47: Nouvelles annonces C2C publiées (M1 = stock initial) | B47: =Parametres!$D$91*(1-IF(Parametres!$B$158=1,Parametres!$B$159,0)) -> 15 | C47: =Parametres!$D$92 -> 2 | D47: =Parametres!$D$92 -> 2 | E47: =Parametres!$D$92 -> 2 | F47: =Parametres!$D$92 -> 2 | G47: =Parametres!$D$92 -> 2 | H47: =Parametres!$D$92 -> 2 | I47: =Parametres!$D$92 -> 2 | J47: =Parametres!$D$92 -> 2 | ... AK47: =Parametres!$D$92 -> 2
A48: Annonces C2C retirées (churn) | B48: =0 -> 0 | C48: =B49*Parametres!$D$93 -> 0.75 | D48: =C49*Parametres!$D$93 -> 0.8125 | E48: =D49*Parametres!$D$93 -> 0.871875 | F48: =E49*Parametres!$D$93 -> 0.92828125 | G48: =F49*Parametres!$D$93 -> 0.98186719 | H48: =G49*Parametres!$D$93 -> 1.0327738 | I48: =H49*Parametres!$D$93 -> 1.0811351 | J48: =I49*Parametres!$D$93 -> 1.1270784 | ... AK48: =AJ49*Parametres!$D$93 -> 1.7814692
A49: Annonces C2C actives (stock × (1 − churn) + nouveaux) | B49: =B47 -> 15 | C49: =B49*(1-Parametres!$D$93)+C47 -> 16.25 | D49: =C49*(1-Parametres!$D$93)+D47 -> 17.4375 | E49: =D49*(1-Parametres!$D$93)+E47 -> 18.565625 | F49: =E49*(1-Parametres!$D$93)+F47 -> 19.637344 | G49: =F49*(1-Parametres!$D$93)+G47 -> 20.655477 | H49: =G49*(1-Parametres!$D$93)+H47 -> 21.622703 | I49: =H49*(1-Parametres!$D$93)+I47 -> 22.541568 | J49: =I49*(1-Parametres!$D$93)+J47 -> 23.414489 | ... AK49: =AJ49*(1-Parametres!$D$93)+AK47 -> 35.847915
A50: Capacité mensuelle (actifs × max par mois × fill rate max) | B50: =B49*Parametres!$D$94*Parametres!$D$95 -> 12 | C50: =C49*Parametres!$D$94*Parametres!$D$95 -> 13 | D50: =D49*Parametres!$D$94*Parametres!$D$95 -> 13.95 | E50: =E49*Parametres!$D$94*Parametres!$D$95 -> 14.8525 | F50: =F49*Parametres!$D$94*Parametres!$D$95 -> 15.709875 | G50: =G49*Parametres!$D$94*Parametres!$D$95 -> 16.524381 | H50: =H49*Parametres!$D$94*Parametres!$D$95 -> 17.298162 | I50: =I49*Parametres!$D$94*Parametres!$D$95 -> 18.033254 | ... AK50: =AK49*Parametres!$D$94*Parametres!$D$95 -> 28.678332
A51: Demande (locations C2C) — croissance section 7 × multiplicateur acquisition | B51: =Parametres!$D$39*(1-IF(Parametres!$B$158=1,Parametres!$B$159,0)) -> 12 | C51: =B51*(1+IF(C8=1,0,CHOOSE(C$2,Parametres!$F$54,Parametres!$G$54,Parametres!$H$54)*C7)) -> 12.18 | D51: =C51*(1+IF(D8=1,0,CHOOSE(D$2,Parametres!$F$54,Parametres!$G$54,Parametres!$H$54)*D7)) -> 12.3627 | E51: =D51*(1+IF(E8=1,0,CHOOSE(E$2,Parametres!$F$54,Parametres!$G$54,Parametres!$H$54)*E7)) -> 12.54814 | F51: =E51*(1+IF(F8=1,0,CHOOSE(F$2,Parametres!$F$54,Parametres!$G$54,Parametres!$H$54)*F7)) -> 12.736363 | G51: =F51*(1+IF(G8=1,0,CHOOSE(G$2,Parametres!$F$54,Parametres!$G$54,Parametres!$H$54)*G7)) -> 12.927408 | H51: =G51*(1+IF(H8=1,0,CHOOSE(H$2,Parametres!$F$54,Parametres!$G$54,Parametres!$H$54)*H7)) -> 13.121319 | I51: =H51*(1+IF(I8=1,0,CHOOSE(I$2,Parametres!$F$54,Parametres!$G$54,Parametres!$H$54)*I7)) -> 13.318139 | J51: =I51*(1+IF(J8=1,0,CHOOSE(J$2,Parametres!$F$54,Parametres!$G$54,Parametres!$H$54)*J7)) -> 13.517911 | ... AK51: =AJ51*(1+IF(AK8=1,0,CHOOSE(AK$2,Parametres!$F$54,Parametres!$G$54,Parametres!$H$54)*AK7)) -> 19.148629
A52: Locations C2C réalisées = MIN(demande, capacité) | B52: =MIN(B51,B50) -> 12 | C52: =MIN(C51,C50) -> 12.18 | D52: =MIN(D51,D50) -> 12.3627 | E52: =MIN(E51,E50) -> 12.54814 | F52: =MIN(F51,F50) -> 12.736363 | G52: =MIN(G51,G50) -> 12.927408 | H52: =MIN(H51,H50) -> 13.121319 | I52: =MIN(I51,I50) -> 13.318139 | ... AK52: =MIN(AK51,AK50) -> 19.148629
A53: Demande non servie (pénurie d'offre) | B53: =B51-B52 -> 0 | C53: =C51-C52 -> 0 | D53: =D51-D52 -> 0 | E53: =E51-E52 -> 0 | F53: =F51-F52 -> 0 | G53: =G51-G52 -> 0 | H53: =H51-H52 -> 0 | I53: =I51-I52 -> 0 | ... AK53: =AK51-AK52 -> 0
A54: Taux d'utilisation de la capacité brute (réalisées / (actifs × max)) | B54: =IF(B49*Parametres!$D$94=0,0,B52/(B49*Parametres!$D$94)) -> 0.8 | C54: =IF(C49*Parametres!$D$94=0,0,C52/(C49*Parametres!$D$94)) -> 0.74953846 | D54: =IF(D49*Parametres!$D$94=0,0,D52/(D49*Parametres!$D$94)) -> 0.70897204 | E54: =IF(E49*Parametres!$D$94=0,0,E52/(E49*Parametres!$D$94)) -> 0.67588032 | F54: =IF(F49*Parametres!$D$94=0,0,F52/(F49*Parametres!$D$94)) -> 0.64857869 | G54: =IF(G49*Parametres!$D$94=0,0,G52/(G49*Parametres!$D$94)) -> 0.62585862 | H54: =IF(H49*Parametres!$D$94=0,0,H52/(H49*Parametres!$D$94)) -> 0.60683067 | I54: =IF(I49*Parametres!$D$94=0,0,I52/(I49*Parametres!$D$94)) -> 0.59082577 | ... AK54: =IF(AK49*Parametres!$D$94=0,0,AK52/(AK49*Parametres!$D$94)) -> 0.53416297
A55: Panier / loyer moyen (indexé par an) | B55: =Parametres!$D$40*(1+Parametres!$D$46)^(B$2-1) -> 10000 | C55: =Parametres!$D$40*(1+Parametres!$D$46)^(C$2-1) -> 10000 | D55: =Parametres!$D$40*(1+Parametres!$D$46)^(D$2-1) -> 10000 | E55: =Parametres!$D$40*(1+Parametres!$D$46)^(E$2-1) -> 10000 | F55: =Parametres!$D$40*(1+Parametres!$D$46)^(F$2-1) -> 10000 | G55: =Parametres!$D$40*(1+Parametres!$D$46)^(G$2-1) -> 10000 | H55: =Parametres!$D$40*(1+Parametres!$D$46)^(H$2-1) -> 10000 | I55: =Parametres!$D$40*(1+Parametres!$D$46)^(I$2-1) -> 10000 | ... AK55: =Parametres!$D$40*(1+Parametres!$D$46)^(AK$2-1) -> 11664
A56: GMV locations C2C | B56: =B52*B55 -> 120000 | C56: =C52*C55 -> 121800 | D56: =D52*D55 -> 123627 | E56: =E52*E55 -> 125481.4 | F56: =F52*F55 -> 127363.63 | G56: =G52*G55 -> 129274.08 | H56: =H52*H55 -> 131213.19 | I56: =I52*I55 -> 133181.39 | ... AK56: =AK52*AK55 -> 223349.61
A57: CA commissions locations particuliers | B57: =B56*Parametres!$D$41 -> 15600 | C57: =C56*Parametres!$D$41 -> 15834 | D57: =D56*Parametres!$D$41 -> 16071.51 | E57: =E56*Parametres!$D$41 -> 16312.583 | F57: =F56*Parametres!$D$41 -> 16557.271 | G57: =G56*Parametres!$D$41 -> 16805.63 | H57: =H56*Parametres!$D$41 -> 17057.715 | I57: =I56*Parametres!$D$41 -> 17313.581 | ... AK57: =AK56*Parametres!$D$41 -> 29035.449
A59: TOTAUX
A60: GMV total (prestations + locations) | B60: =B23+B43+B56 -> 2970000 | C60: =C23+C43+C56 -> 3028350 | D60: =D23+D43+D56 -> 3087849.9 | E60: =E23+E43+E56 -> 3148522.4 | F60: =F23+F43+F56 -> 3210390.7 | G60: =G23+G43+G56 -> 3273478.4 | H60: =H23+H43+H56 -> 3337809.6 | I60: =I23+I43+I56 -> 3403408.9 | ... AK60: =AK23+AK43+AK56 -> 7369664.5
A61: MRR (abonnements Ampio+ + vidéo) | B61: =B17+B31 -> 1020000 | C61: =C17+C31 -> 1073400 | D61: =D17+D31 -> 1129038 | E61: =E17+E31 -> 1187038.9 | F61: =F17+F31 -> 1247533.3 | G61: =G17+G31 -> 1310658.2 | H61: =H17+H31 -> 1376556.9 | I61: =I17+I31 -> 1445379.5 | ... AK61: =AK17+AK31 -> 5294358.1
A62: CA transactionnel (commissions) | B62: =B24+B44+B57 -> 374700 | C62: =C24+C44+C57 -> 381988.42 | D62: =D24+D44+D57 -> 389419.15 | E62: =E24+E44+E57 -> 396994.97 | F62: =F24+F44+F57 -> 404718.72 | G62: =G24+G44+G57 -> 412593.29 | H62: =H24+H44+H57 -> 479745.18 | I62: =I24+I44+I57 -> 489112.81 | ... AK62: =AK24+AK44+AK57 -> 1057285.1
A63: CHIFFRE D'AFFAIRES TOTAL (IFRS 15 — agent : commissions + abonnements) | B63: =B61+B62 -> 1394700 | C63: =C61+C62 -> 1455388.4 | D63: =D61+D62 -> 1518457.2 | E63: =E61+E62 -> 1584033.8 | F63: =F61+F62 -> 1652252 | G63: =G61+G62 -> 1723251.5 | H63: =H61+H62 -> 1856302 | I63: =I61+I62 -> 1934492.3 | ... AK63: =AK61+AK62 -> 6351643.2
A64: Transactions réalisées (prestations + locations pro + C2C) | B64: =B19+B39+B52 -> 102 | C64: =C19+C39+C52 -> 103.95 | D64: =D19+D39+D52 -> 105.93756 | E64: =E19+E39+E52 -> 107.96341 | F64: =F19+F39+F52 -> 110.02829 | G64: =G19+G39+G52 -> 112.13295 | H64: =H19+H39+H52 -> 114.27817 | I64: =I19+I39+I52 -> 116.46474 | ... AK64: =AK19+AK39+AK52 -> 211.79883
A65: Nouveaux clients DEMANDE estimés (part transactions nouveaux ÷ transactions par client) | B65: =Parametres!$D$72*B64/Parametres!$D$73 -> 15.3 | C65: =Parametres!$D$72*C64/Parametres!$D$73 -> 15.5925 | D65: =Parametres!$D$72*D64/Parametres!$D$73 -> 15.890634 | E65: =Parametres!$D$72*E64/Parametres!$D$73 -> 16.194511 | F65: =Parametres!$D$72*F64/Parametres!$D$73 -> 16.504243 | G65: =Parametres!$D$72*G64/Parametres!$D$73 -> 16.819943 | H65: =Parametres!$D$72*H64/Parametres!$D$73 -> 17.141726 | I65: =Parametres!$D$72*I64/Parametres!$D$73 -> 17.469711 | ... AK65: =Parametres!$D$72*AK64/Parametres!$D$73 -> 31.769824
A66: Nouveaux clients à vérifier (prestataires + loueurs + vidéo + demande) | B66: =B11+B34+B27+B65 -> 63.3 | C66: =C11+C34+C27+C65 -> 20.7175 | D66: =D11+D34+D27+D65 -> 21.071884 | E66: =E11+E34+E27+E65 -> 21.434824 | F66: =F11+F34+F27+F65 -> 21.806571 | G66: =G11+G34+G27+G65 -> 22.187387 | H66: =H11+H34+H27+H65 -> 22.577543 | I66: =I11+I34+I27+I65 -> 22.977319 | ... AK66: =AK11+AK34+AK27+AK65 -> 45.721955
A67: GMV perdu faute d'offre (demande non servie × panier) | B67: =B20*B22+B40*B42+B53*B55 -> 0 | C67: =C20*C22+C40*C42+C53*C55 -> 0 | D67: =D20*D22+D40*D42+D53*D55 -> 0 | E67: =E20*E22+E40*E42+E53*E55 -> 0 | F67: =F20*F22+F40*F42+F53*F55 -> 0 | G67: =G20*G22+G40*G42+G53*G55 -> 0 | H67: =H20*H22+H40*H42+H53*H55 -> 0 | I67: =I20*I22+I40*I42+I53*I55 -> 0 | ... AK67: =AK20*AK22+AK40*AK42+AK53*AK55 -> 0
A69: EMBAUCHE DU COLLABORATEUR 2
A70: Collaborateur 2 actif (0/1) — déclencheur trésorerie + EBITDA, mois minimum section 14 | B70: =0 -> 0 | C70: =IF(C$3<Parametres!$D$126,0,IF(B70=1,1,IF(AND(N(C$3>=Parametres!$D$128+1),INDEX(Tresorerie!$C$25:$AM$25,C$3)>Parametres!$D$127,INDEX(Tresorerie!$C$25:$AM$25,C$3-1)>Parametres!$D$127,INDEX(Tresorerie!$C$25:$AM$25,C$3-2)>Parametres!$D$127,IF(Parametres!$D$129=1,INDEX('P&L'!$B$18:$AK$18,C$3-1)>0,TRUE),IF(Parametres!$D$129=1,INDEX('P&L'!$B$18:$AK$18,C$3-2)>0,TRUE),IF(Parametres!$D$129=1,INDEX('P&L'!$B$18:$AK$18,C$3-3)>0,TRUE)),1,0))) -> 0 | D70: =IF(D$3<Parametres!$D$126,0,IF(C70=1,1,IF(AND(N(D$3>=Parametres!$D$128+1),INDEX(Tresorerie!$C$25:$AM$25,D$3)>Parametres!$D$127,INDEX(Tresorerie!$C$25:$AM$25,D$3-1)>Parametres!$D$127,INDEX(Tresorerie!$C$25:$AM$25,D$3-2)>Parametres!$D$127,IF(Parametres!$D$129=1,INDEX('P&L'!$B$18:$AK$18,D$3-1)>0,TRUE),IF(Parametres!$D$129=1,INDEX('P&L'!$B$18:$AK$18,D$3-2)>0,TRUE),IF(Parametres!$D$129=1,INDEX('P&L'!$B$18:$AK$18,D$3-3)>0,TRUE)),1,0))) -> 0 | E70: =IF(E$3<Parametres!$D$126,0,IF(D70=1,1,IF(AND(N(E$3>=Parametres!$D$128+1),INDEX(Tresorerie!$C$25:$AM$25,E$3)>Parametres!$D$127,INDEX(Tresorerie!$C$25:$AM$25,E$3-1)>Parametres!$D$127,INDEX(Tresorerie!$C$25:$AM$25,E$3-2)>Parametres!$D$127,IF(Parametres!$D$129=1,INDEX('P&L'!$B$18:$AK$18,E$3-1)>0,TRUE),IF(Parametres!$D$129=1,INDEX('P&L'!$B$18:$AK$18,E$3-2)>0,TRUE),IF(Parametres!$D$129=1,INDEX('P&L'!$B$18:$AK$18,E$3-3)>0,TRUE)),1,0))) -> 0 | F70: =IF(F$3<Parametres!$D$126,0,IF(E70=1,1,IF(AND(N(F$3>=Parametres!$D$128+1),INDEX(Tresorerie!$C$25:$AM$25,F$3)>Parametres!$D$127,INDEX(Tresorerie!$C$25:$AM$25,F$3-1)>Parametres!$D$127,INDEX(Tresorerie!$C$25:$AM$25,F$3-2)>Parametres!$D$127,IF(Parametres!$D$129=1,INDEX('P&L'!$B$18:$AK$18,F$3-1)>0,TRUE),IF(Parametres!$D$129=1,INDEX('P&L'!$B$18:$AK$18,F$3-2)>0,TRUE),IF(Parametres!$D$129=1,INDEX('P&L'!$B$18:$AK$18,F$3-3)>0,TRUE)),1,0))) -> 0 | G70: =IF(G$3<Parametres!$D$126,0,IF(F70=1,1,IF(AND(N(G$3>=Parametres!$D$128+1),INDEX(Tresorerie!$C$25:$AM$25,G$3)>Parametres!$D$127,INDEX(Tresorerie!$C$25:$AM$25,G$3-1)>Parametres!$D$127,INDEX(Tresorerie!$C$25:$AM$25,G$3-2)>Parametres!$D$127,IF(Parametres!$D$129=1,INDEX('P&L'!$B$18:$AK$18,G$3-1)>0,TRUE),IF(Parametres!$D$129=1,INDEX('P&L'!$B$18:$AK$18,G$3-2)>0,TRUE),IF(Parametres!$D$129=1,INDEX('P&L'!$B$18:$AK$18,G$3-3)>0,TRUE)),1,0))) -> 0 | H70: =IF(H$3<Parametres!$D$126,0,IF(G70=1,1,IF(AND(N(H$3>=Parametres!$D$128+1),INDEX(Tresorerie!$C$25:$AM$25,H$3)>Parametres!$D$127,INDEX(Tresorerie!$C$25:$AM$25,H$3-1)>Parametres!$D$127,INDEX(Tresorerie!$C$25:$AM$25,H$3-2)>Parametres!$D$127,IF(Parametres!$D$129=1,INDEX('P&L'!$B$18:$AK$18,H$3-1)>0,TRUE),IF(Parametres!$D$129=1,INDEX('P&L'!$B$18:$AK$18,H$3-2)>0,TRUE),IF(Parametres!$D$129=1,INDEX('P&L'!$B$18:$AK$18,H$3-3)>0,TRUE)),1,0))) -> 0 | I70: =IF(I$3<Parametres!$D$126,0,IF(H70=1,1,IF(AND(N(I$3>=Parametres!$D$128+1),INDEX(Tresorerie!$C$25:$AM$25,I$3)>Parametres!$D$127,INDEX(Tresorerie!$C$25:$AM$25,I$3-1)>Parametres!$D$127,INDEX(Tresorerie!$C$25:$AM$25,I$3-2)>Parametres!$D$127,IF(Parametres!$D$129=1,INDEX('P&L'!$B$18:$AK$18,I$3-1)>0,TRUE),IF(Parametres!$D$129=1,INDEX('P&L'!$B$18:$AK$18,I$3-2)>0,TRUE),IF(Parametres!$D$129=1,INDEX('P&L'!$B$18:$AK$18,I$3-3)>0,TRUE)),1,0))) -> 0 | J70: =IF(J$3<Parametres!$D$126,0,IF(I70=1,1,IF(AND(N(J$3>=Parametres!$D$128+1),INDEX(Tresorerie!$C$25:$AM$25,J$3)>Parametres!$D$127,INDEX(Tresorerie!$C$25:$AM$25,J$3-1)>Parametres!$D$127,INDEX(Tresorerie!$C$25:$AM$25,J$3-2)>Parametres!$D$127,IF(Parametres!$D$129=1,INDEX('P&L'!$B$18:$AK$18,J$3-1)>0,TRUE),IF(Parametres!$D$129=1,INDEX('P&L'!$B$18:$AK$18,J$3-2)>0,TRUE),IF(Parametres!$D$129=1,INDEX('P&L'!$B$18:$AK$18,J$3-3)>0,TRUE)),1,0))) -> 0 | ... AK70: =IF(AK$3<Parametres!$D$126,0,IF(AJ70=1,1,IF(AND(N(AK$3>=Parametres!$D$128+1),INDEX(Tresorerie!$C$25:$AM$25,AK$3)>Parametres!$D$127,INDEX(Tresorerie!$C$25:$AM$25,AK$3-1)>Parametres!$D$127,INDEX(Tresorerie!$C$25:$AM$25,AK$3-2)>Parametres!$D$127,IF(Parametres!$D$129=1,INDEX('P&L'!$B$18:$AK$18,AK$3-1)>0,TRUE),IF(Parametres!$D$129=1,INDEX('P&L'!$B$18:$AK$18,AK$3-2)>0,TRUE),IF(Parametres!$D$129=1,INDEX('P&L'!$B$18:$AK$18,AK$3-3)>0,TRUE)),1,0))) -> 1

Sheet Contribution
A1: CASCADE DE CONTRIBUTION — coûts variables suivant le volume (MGA)
A2: Année | B2: ='P&L'!B2 -> 1 | C2: ='P&L'!C2 -> 1 | D2: ='P&L'!D2 -> 1 | E2: ='P&L'!E2 -> 1 | F2: ='P&L'!F2 -> 1 | G2: ='P&L'!G2 -> 1 | H2: ='P&L'!H2 -> 1 | I2: ='P&L'!I2 -> 1 | ... AK2: ='P&L'!AK2 -> 3
A3: Mois | B3: ='P&L'!B3 -> 1 | C3: ='P&L'!C3 -> 2 | D3: ='P&L'!D3 -> 3 | E3: ='P&L'!E3 -> 4 | F3: ='P&L'!F3 -> 5 | G3: ='P&L'!G3 -> 6 | H3: ='P&L'!H3 -> 7 | I3: ='P&L'!I3 -> 8 | ... AK3: ='P&L'!AK3 -> 36
A5: Chiffre d'affaires (IFRS 15) | B5: ='P&L'!B5 -> 1394700 | C5: ='P&L'!C5 -> 1455388.4 | D5: ='P&L'!D5 -> 1518457.2 | E5: ='P&L'!E5 -> 1584033.8 | F5: ='P&L'!F5 -> 1652252 | G5: ='P&L'!G5 -> 1723251.5 | H5: ='P&L'!H5 -> 1856302 | I5: ='P&L'!I5 -> 1934492.3 | ... AK5: ='P&L'!AK5 -> 6351643.2
A6: dont MM 3 % (abo Ampio+ + GMV, hors vidéo) | B6: =-('Plan ventes'!B17+'Plan ventes'!B23+'Plan ventes'!B43+'Plan ventes'!B56)*Parametres!$D$105 -> -90900 | C6: =-('Plan ventes'!C17+'Plan ventes'!C23+'Plan ventes'!C43+'Plan ventes'!C56)*Parametres!$D$105 -> -92812.5 | D6: =-('Plan ventes'!D17+'Plan ventes'!D23+'Plan ventes'!D43+'Plan ventes'!D56)*Parametres!$D$105 -> -94754.637 | E6: =-('Plan ventes'!E17+'Plan ventes'!E23+'Plan ventes'!E43+'Plan ventes'!E56)*Parametres!$D$105 -> -96727.238 | F6: =-('Plan ventes'!F17+'Plan ventes'!F23+'Plan ventes'!F43+'Plan ventes'!F56)*Parametres!$D$105 -> -98731.14 | G6: =-('Plan ventes'!G17+'Plan ventes'!G23+'Plan ventes'!G43+'Plan ventes'!G56)*Parametres!$D$105 -> -100767.19 | H6: =-('Plan ventes'!H17+'Plan ventes'!H23+'Plan ventes'!H43+'Plan ventes'!H56)*Parametres!$D$105 -> -102836.24 | I6: =-('Plan ventes'!I17+'Plan ventes'!I23+'Plan ventes'!I43+'Plan ventes'!I56)*Parametres!$D$105 -> -104939.16 | ... AK6: =-('Plan ventes'!AK17+'Plan ventes'!AK23+'Plan ventes'!AK43+'Plan ventes'!AK56)*Parametres!$D$105 -> -231303.92
A7: dont SMS (Ampio + C2C) | B7: =-('Plan ventes'!B19+'Plan ventes'!B52)*Parametres!$D$104*(1+Parametres!$D$46)^(B$2-1) -> -6213.54 | C7: =-('Plan ventes'!C19+'Plan ventes'!C52)*Parametres!$D$104*(1+Parametres!$D$46)^(C$2-1) -> -6333.5256 | D7: =-('Plan ventes'!D19+'Plan ventes'!D52)*Parametres!$D$104*(1+Parametres!$D$46)^(D$2-1) -> -6455.8466 | E7: =-('Plan ventes'!E19+'Plan ventes'!E52)*Parametres!$D$104*(1+Parametres!$D$46)^(E$2-1) -> -6580.5488 | F7: =-('Plan ventes'!F19+'Plan ventes'!F52)*Parametres!$D$104*(1+Parametres!$D$46)^(F$2-1) -> -6707.6789 | G7: =-('Plan ventes'!G19+'Plan ventes'!G52)*Parametres!$D$104*(1+Parametres!$D$46)^(G$2-1) -> -6837.2843 | H7: =-('Plan ventes'!H19+'Plan ventes'!H52)*Parametres!$D$104*(1+Parametres!$D$46)^(H$2-1) -> -6969.4136 | I7: =-('Plan ventes'!I19+'Plan ventes'!I52)*Parametres!$D$104*(1+Parametres!$D$46)^(I$2-1) -> -7104.1163 | ... AK7: =-('Plan ventes'!AK19+'Plan ventes'!AK52)*Parametres!$D$104*(1+Parametres!$D$46)^(AK$2-1) -> -15078.213
A8: dont support / modération (Ar / transaction) | B8: =-'Plan ventes'!B64*Parametres!$D$106 -> -102000 | C8: =-'Plan ventes'!C64*Parametres!$D$106 -> -103950 | D8: =-'Plan ventes'!D64*Parametres!$D$106 -> -105937.56 | E8: =-'Plan ventes'!E64*Parametres!$D$106 -> -107963.41 | F8: =-'Plan ventes'!F64*Parametres!$D$106 -> -110028.29 | G8: =-'Plan ventes'!G64*Parametres!$D$106 -> -112132.95 | H8: =-'Plan ventes'!H64*Parametres!$D$106 -> -114278.17 | I8: =-'Plan ventes'!I64*Parametres!$D$106 -> -116464.74 | ... AK8: =-'Plan ventes'!AK64*Parametres!$D$106 -> -211798.83
A9: dont vérification nouveaux clients (prestataires, loueurs, vidéo, demande) | B9: =-'Plan ventes'!B66*Parametres!$D$107 -> -189900 | C9: =-'Plan ventes'!C66*Parametres!$D$107 -> -62152.5 | D9: =-'Plan ventes'!D66*Parametres!$D$107 -> -63215.652 | E9: =-'Plan ventes'!E66*Parametres!$D$107 -> -64304.471 | F9: =-'Plan ventes'!F66*Parametres!$D$107 -> -65419.713 | G9: =-'Plan ventes'!G66*Parametres!$D$107 -> -66562.162 | H9: =-'Plan ventes'!H66*Parametres!$D$107 -> -67732.629 | I9: =-'Plan ventes'!I66*Parametres!$D$107 -> -68931.956 | ... AK9: =-'Plan ventes'!AK66*Parametres!$D$107 -> -137165.87
A10: dont provision litiges (% GMV) | B10: =-'Plan ventes'!B60*Parametres!$D$108 -> -29700 | C10: =-'Plan ventes'!C60*Parametres!$D$108 -> -30283.5 | D10: =-'Plan ventes'!D60*Parametres!$D$108 -> -30878.499 | E10: =-'Plan ventes'!E60*Parametres!$D$108 -> -31485.224 | F10: =-'Plan ventes'!F60*Parametres!$D$108 -> -32103.907 | G10: =-'Plan ventes'!G60*Parametres!$D$108 -> -32734.784 | H10: =-'Plan ventes'!H60*Parametres!$D$108 -> -33378.096 | I10: =-'Plan ventes'!I60*Parametres!$D$108 -> -34034.089 | ... AK10: =-'Plan ventes'!AK60*Parametres!$D$108 -> -73696.645
A11: Total coûts variables | B11: =B6+B7+B8+B9+B10 -> -418713.54 | C11: =C6+C7+C8+C9+C10 -> -295532.03 | D11: =D6+D7+D8+D9+D10 -> -301242.19 | E11: =E6+E7+E8+E9+E10 -> -307060.89 | F11: =F6+F7+F8+F9+F10 -> -312990.73 | G11: =G6+G7+G8+G9+G10 -> -319034.37 | H11: =H6+H7+H8+H9+H10 -> -325194.55 | I11: =I6+I7+I8+I9+I10 -> -331474.06 | ... AK11: =AK6+AK7+AK8+AK9+AK10 -> -669043.47
A12: MARGE DE CONTRIBUTION | B12: =B5+B11 -> 975986.46 | C12: =C5+C11 -> 1159856.4 | D12: =D5+D11 -> 1217215 | E12: =E5+E11 -> 1276972.9 | F12: =F5+F11 -> 1339261.3 | G12: =G5+G11 -> 1404217.1 | H12: =H5+H11 -> 1531107.5 | I12: =I5+I11 -> 1603018.2 | ... AK12: =AK5+AK11 -> 5682599.8
A13: % contribution | B13: =IF(B5=0,0,B12/B5) -> 0.69978236 | C13: =IF(C5=0,0,C12/C5) -> 0.79693941 | D13: =IF(D5=0,0,D12/D5) -> 0.80161298 | E13: =IF(E5=0,0,E12/E5) -> 0.80615257 | F13: =IF(F5=0,0,F12/F5) -> 0.8105672 | G13: =IF(G5=0,0,G12/G5) -> 0.81486488 | H13: =IF(H5=0,0,H12/H5) -> 0.82481593 | I13: =IF(I5=0,0,I12/I5) -> 0.82865062 | ... AK13: =IF(AK5=0,0,AK12/AK5) -> 0.89466608
A15: Publicité (budget saisi par année, Parametres section 9) | B15: =-'Plan ventes'!B6 -> -400000 | C15: =-'Plan ventes'!C6 -> -400000 | D15: =-'Plan ventes'!D6 -> -400000 | E15: =-'Plan ventes'!E6 -> -400000 | F15: =-'Plan ventes'!F6 -> -400000 | G15: =-'Plan ventes'!G6 -> -400000 | H15: =-'Plan ventes'!H6 -> -400000 | I15: =-'Plan ventes'!I6 -> -400000 | ... AK15: =-'Plan ventes'!AK6 -> -600000
A16: Contribution après pub | B16: =B12+B15 -> 575986.46 | C16: =C12+C15 -> 759856.4 | D16: =D12+D15 -> 817214.96 | E16: =E12+E15 -> 876972.94 | F16: =F12+F15 -> 939261.28 | G16: =G12+G15 -> 1004217.1 | H16: =H12+H15 -> 1131107.5 | I16: =I12+I15 -> 1203018.2 | ... AK16: =AK12+AK15 -> 5082599.8
A18: OPEX fixes (loyer, salaires chargés, hébergement, storage, modération, accompagnement) | B18: ='P&L'!B17-B15 -> -2405583 | C18: ='P&L'!C17-C15 -> -2405583 | D18: ='P&L'!D17-D15 -> -2405583 | E18: ='P&L'!E17-E15 -> -2405583 | F18: ='P&L'!F17-F15 -> -2405583 | G18: ='P&L'!G17-G15 -> -2405583 | H18: ='P&L'!H17-H15 -> -2405583 | I18: ='P&L'!I17-I15 -> -2405583 | ... AK18: ='P&L'!AK17-AK15 -> -3356412.8
A19: EBITDA (contrôle = P&L) | B19: =B16+B18 -> -1829596.5 | C19: =C16+C18 -> -1645726.6 | D19: =D16+D18 -> -1588368 | E19: =E16+E18 -> -1528610.1 | F19: =F16+F18 -> -1466321.7 | G19: =G16+G18 -> -1401365.9 | H19: =H16+H18 -> -1274475.5 | I19: =I16+I18 -> -1202564.8 | ... AK19: =AK16+AK18 -> 1726187
A20: Écart vs P&L EBITDA (doit = 0) | B20: =B19-'P&L'!B18 -> 0 | C20: =C19-'P&L'!C18 -> 0 | D20: =D19-'P&L'!D18 -> 0 | E20: =E19-'P&L'!E18 -> 0 | F20: =F19-'P&L'!F18 -> 0 | G20: =G19-'P&L'!G18 -> 0 | H20: =H19-'P&L'!H18 -> 0 | I20: =I19-'P&L'!I18 -> 0 | ... AK20: =AK19-'P&L'!AK18 -> 0
A22: Lecture : les coûts variables suivent le volume (transactions réalisées, nouveaux clients, GMV). Les OPEX fixes ne bougent qu'avec l'inflation, le scénario, le stress test et l'embauche du collab 2. Taux unitaires : Parametres section 12 ; budget pub : section 9.

Sheet P&L
A1: COMPTE DE RÉSULTAT — cascade de contribution (MGA) — M1–M36
A2: Année | B2: ='Plan ventes'!B2 -> 1 | C2: ='Plan ventes'!C2 -> 1 | D2: ='Plan ventes'!D2 -> 1 | E2: ='Plan ventes'!E2 -> 1 | F2: ='Plan ventes'!F2 -> 1 | G2: ='Plan ventes'!G2 -> 1 | H2: ='Plan ventes'!H2 -> 1 | I2: ='Plan ventes'!I2 -> 1 | ... AK2: ='Plan ventes'!AK2 -> 3
A3: Mois | B3: ='Plan ventes'!B3 -> 1 | C3: ='Plan ventes'!C3 -> 2 | D3: ='Plan ventes'!D3 -> 3 | E3: ='Plan ventes'!E3 -> 4 | F3: ='Plan ventes'!F3 -> 5 | G3: ='Plan ventes'!G3 -> 6 | H3: ='Plan ventes'!H3 -> 7 | I3: ='Plan ventes'!I3 -> 8 | ... AK3: ='Plan ventes'!AK3 -> 36
A5: Chiffre d'affaires (commissions + abonnements) | B5: ='Plan ventes'!B63-IF(Parametres!$B$158=1,Parametres!$B$164*'Plan ventes'!B60,0) -> 1394700 | C5: ='Plan ventes'!C63-IF(Parametres!$B$158=1,Parametres!$B$164*'Plan ventes'!C60,0) -> 1455388.4 | D5: ='Plan ventes'!D63-IF(Parametres!$B$158=1,Parametres!$B$164*'Plan ventes'!D60,0) -> 1518457.2 | E5: ='Plan ventes'!E63-IF(Parametres!$B$158=1,Parametres!$B$164*'Plan ventes'!E60,0) -> 1584033.8 | F5: ='Plan ventes'!F63-IF(Parametres!$B$158=1,Parametres!$B$164*'Plan ventes'!F60,0) -> 1652252 | G5: ='Plan ventes'!G63-IF(Parametres!$B$158=1,Parametres!$B$164*'Plan ventes'!G60,0) -> 1723251.5 | H5: ='Plan ventes'!H63-IF(Parametres!$B$158=1,Parametres!$B$164*'Plan ventes'!H60,0) -> 1856302 | I5: ='Plan ventes'!I63-IF(Parametres!$B$158=1,Parametres!$B$164*'Plan ventes'!I60,0) -> 1934492.3 | ... AK5: ='Plan ventes'!AK63-IF(Parametres!$B$158=1,Parametres!$B$164*'Plan ventes'!AK60,0) -> 6351643.2
A6: dont revenus récurrents (MRR) | B6: ='Plan ventes'!B61 -> 1020000 | C6: ='Plan ventes'!C61 -> 1073400 | D6: ='Plan ventes'!D61 -> 1129038 | E6: ='Plan ventes'!E61 -> 1187038.9 | F6: ='Plan ventes'!F61 -> 1247533.3 | G6: ='Plan ventes'!G61 -> 1310658.2 | H6: ='Plan ventes'!H61 -> 1376556.9 | I6: ='Plan ventes'!I61 -> 1445379.5 | ... AK6: ='Plan ventes'!AK61 -> 5294358.1
A7: Coûts variables (Mobile Money + SMS + support + vérification + litiges) | B7: =-(('Plan ventes'!B17+'Plan ventes'!B23+'Plan ventes'!B43+'Plan ventes'!B56)*Parametres!$D$105+('Plan ventes'!B19+'Plan ventes'!B52)*Parametres!$D$104*(1+Parametres!$D$46)^(B$2-1)+('Plan ventes'!B64)*Parametres!$D$106+'Plan ventes'!B66*Parametres!$D$107+'Plan ventes'!B60*Parametres!$D$108) -> -418713.54 | C7: =-(('Plan ventes'!C17+'Plan ventes'!C23+'Plan ventes'!C43+'Plan ventes'!C56)*Parametres!$D$105+('Plan ventes'!C19+'Plan ventes'!C52)*Parametres!$D$104*(1+Parametres!$D$46)^(C$2-1)+('Plan ventes'!C64)*Parametres!$D$106+'Plan ventes'!C66*Parametres!$D$107+'Plan ventes'!C60*Parametres!$D$108) -> -295532.03 | D7: =-(('Plan ventes'!D17+'Plan ventes'!D23+'Plan ventes'!D43+'Plan ventes'!D56)*Parametres!$D$105+('Plan ventes'!D19+'Plan ventes'!D52)*Parametres!$D$104*(1+Parametres!$D$46)^(D$2-1)+('Plan ventes'!D64)*Parametres!$D$106+'Plan ventes'!D66*Parametres!$D$107+'Plan ventes'!D60*Parametres!$D$108) -> -301242.19 | E7: =-(('Plan ventes'!E17+'Plan ventes'!E23+'Plan ventes'!E43+'Plan ventes'!E56)*Parametres!$D$105+('Plan ventes'!E19+'Plan ventes'!E52)*Parametres!$D$104*(1+Parametres!$D$46)^(E$2-1)+('Plan ventes'!E64)*Parametres!$D$106+'Plan ventes'!E66*Parametres!$D$107+'Plan ventes'!E60*Parametres!$D$108) -> -307060.89 | F7: =-(('Plan ventes'!F17+'Plan ventes'!F23+'Plan ventes'!F43+'Plan ventes'!F56)*Parametres!$D$105+('Plan ventes'!F19+'Plan ventes'!F52)*Parametres!$D$104*(1+Parametres!$D$46)^(F$2-1)+('Plan ventes'!F64)*Parametres!$D$106+'Plan ventes'!F66*Parametres!$D$107+'Plan ventes'!F60*Parametres!$D$108) -> -312990.73 | G7: =-(('Plan ventes'!G17+'Plan ventes'!G23+'Plan ventes'!G43+'Plan ventes'!G56)*Parametres!$D$105+('Plan ventes'!G19+'Plan ventes'!G52)*Parametres!$D$104*(1+Parametres!$D$46)^(G$2-1)+('Plan ventes'!G64)*Parametres!$D$106+'Plan ventes'!G66*Parametres!$D$107+'Plan ventes'!G60*Parametres!$D$108) -> -319034.37 | H7: =-(('Plan ventes'!H17+'Plan ventes'!H23+'Plan ventes'!H43+'Plan ventes'!H56)*Parametres!$D$105+('Plan ventes'!H19+'Plan ventes'!H52)*Parametres!$D$104*(1+Parametres!$D$46)^(H$2-1)+('Plan ventes'!H64)*Parametres!$D$106+'Plan ventes'!H66*Parametres!$D$107+'Plan ventes'!H60*Parametres!$D$108) -> -325194.55 | I7: =-(('Plan ventes'!I17+'Plan ventes'!I23+'Plan ventes'!I43+'Plan ventes'!I56)*Parametres!$D$105+('Plan ventes'!I19+'Plan ventes'!I52)*Parametres!$D$104*(1+Parametres!$D$46)^(I$2-1)+('Plan ventes'!I64)*Parametres!$D$106+'Plan ventes'!I66*Parametres!$D$107+'Plan ventes'!I60*Parametres!$D$108) -> -331474.06 | ... AK7: =-(('Plan ventes'!AK17+'Plan ventes'!AK23+'Plan ventes'!AK43+'Plan ventes'!AK56)*Parametres!$D$105+('Plan ventes'!AK19+'Plan ventes'!AK52)*Parametres!$D$104*(1+Parametres!$D$46)^(AK$2-1)+('Plan ventes'!AK64)*Parametres!$D$106+'Plan ventes'!AK66*Parametres!$D$107+'Plan ventes'!AK60*Parametres!$D$108) -> -669043.47
A8: MARGE DE CONTRIBUTION (CA + coûts variables) | B8: =B5+B7 -> 975986.46 | C8: =C5+C7 -> 1159856.4 | D8: =D5+D7 -> 1217215 | E8: =E5+E7 -> 1276972.9 | F8: =F5+F7 -> 1339261.3 | G8: =G5+G7 -> 1404217.1 | H8: =H5+H7 -> 1531107.5 | I8: =I5+I7 -> 1603018.2 | ... AK8: =AK5+AK7 -> 5682599.8
A9: % marge brute | B9: =IF(B5=0,0,B8/B5) -> 0.69978236 | C9: =IF(C5=0,0,C8/C5) -> 0.79693941 | D9: =IF(D5=0,0,D8/D5) -> 0.80161298 | E9: =IF(E5=0,0,E8/E5) -> 0.80615257 | F9: =IF(F5=0,0,F8/F5) -> 0.8105672 | G9: =IF(G5=0,0,G8/G5) -> 0.81486488 | H9: =IF(H5=0,0,H8/H5) -> 0.82481593 | I9: =IF(I5=0,0,I8/I5) -> 0.82865062 | ... AK9: =IF(AK5=0,0,AK8/AK5) -> 0.89466608
A11: Loyer et domiciliation | B11: =-Parametres!$D$112*(1+Parametres!$D$47)^(B$2-1) -> -125000 | C11: =-Parametres!$D$112*(1+Parametres!$D$47)^(C$2-1) -> -125000 | D11: =-Parametres!$D$112*(1+Parametres!$D$47)^(D$2-1) -> -125000 | E11: =-Parametres!$D$112*(1+Parametres!$D$47)^(E$2-1) -> -125000 | F11: =-Parametres!$D$112*(1+Parametres!$D$47)^(F$2-1) -> -125000 | G11: =-Parametres!$D$112*(1+Parametres!$D$47)^(G$2-1) -> -125000 | H11: =-Parametres!$D$112*(1+Parametres!$D$47)^(H$2-1) -> -125000 | I11: =-Parametres!$D$112*(1+Parametres!$D$47)^(I$2-1) -> -125000 | ... AK11: =-Parametres!$D$112*(1+Parametres!$D$47)^(AK$2-1) -> -145800
A12: Salaires chargés — fondateur + collab 1 (+ collab 2 si actif), charges patronales incluses | B12: =-(((Parametres!$D$113+Parametres!$D$114)*(1+Parametres!$D$115))*(1+Parametres!$D$47)^(B$2-1)+IF('Plan ventes'!B70=1,Parametres!$D$125*(1+Parametres!$D$115)*(1+Parametres!$D$47)^(B$2-1),0)) -> -2124000 | C12: =-(((Parametres!$D$113+Parametres!$D$114)*(1+Parametres!$D$115))*(1+Parametres!$D$47)^(C$2-1)+IF('Plan ventes'!C70=1,Parametres!$D$125*(1+Parametres!$D$115)*(1+Parametres!$D$47)^(C$2-1),0)) -> -2124000 | D12: =-(((Parametres!$D$113+Parametres!$D$114)*(1+Parametres!$D$115))*(1+Parametres!$D$47)^(D$2-1)+IF('Plan ventes'!D70=1,Parametres!$D$125*(1+Parametres!$D$115)*(1+Parametres!$D$47)^(D$2-1),0)) -> -2124000 | E12: =-(((Parametres!$D$113+Parametres!$D$114)*(1+Parametres!$D$115))*(1+Parametres!$D$47)^(E$2-1)+IF('Plan ventes'!E70=1,Parametres!$D$125*(1+Parametres!$D$115)*(1+Parametres!$D$47)^(E$2-1),0)) -> -2124000 | F12: =-(((Parametres!$D$113+Parametres!$D$114)*(1+Parametres!$D$115))*(1+Parametres!$D$47)^(F$2-1)+IF('Plan ventes'!F70=1,Parametres!$D$125*(1+Parametres!$D$115)*(1+Parametres!$D$47)^(F$2-1),0)) -> -2124000 | G12: =-(((Parametres!$D$113+Parametres!$D$114)*(1+Parametres!$D$115))*(1+Parametres!$D$47)^(G$2-1)+IF('Plan ventes'!G70=1,Parametres!$D$125*(1+Parametres!$D$115)*(1+Parametres!$D$47)^(G$2-1),0)) -> -2124000 | H12: =-(((Parametres!$D$113+Parametres!$D$114)*(1+Parametres!$D$115))*(1+Parametres!$D$47)^(H$2-1)+IF('Plan ventes'!H70=1,Parametres!$D$125*(1+Parametres!$D$115)*(1+Parametres!$D$47)^(H$2-1),0)) -> -2124000 | I12: =-(((Parametres!$D$113+Parametres!$D$114)*(1+Parametres!$D$115))*(1+Parametres!$D$47)^(I$2-1)+IF('Plan ventes'!I70=1,Parametres!$D$125*(1+Parametres!$D$115)*(1+Parametres!$D$47)^(I$2-1),0)) -> -2124000 | ... AK12: =-(((Parametres!$D$113+Parametres!$D$114)*(1+Parametres!$D$115))*(1+Parametres!$D$47)^(AK$2-1)+IF('Plan ventes'!AK70=1,Parametres!$D$125*(1+Parametres!$D$115)*(1+Parametres!$D$47)^(AK$2-1),0)) -> -3027974.4
A13: Hébergement web | B13: =-Parametres!$D$117*(1+Parametres!$D$47)^(B$2-1) -> -16583 | C13: =-Parametres!$D$117*(1+Parametres!$D$47)^(C$2-1) -> -16583 | D13: =-Parametres!$D$117*(1+Parametres!$D$47)^(D$2-1) -> -16583 | E13: =-Parametres!$D$117*(1+Parametres!$D$47)^(E$2-1) -> -16583 | F13: =-Parametres!$D$117*(1+Parametres!$D$47)^(F$2-1) -> -16583 | G13: =-Parametres!$D$117*(1+Parametres!$D$47)^(G$2-1) -> -16583 | H13: =-Parametres!$D$117*(1+Parametres!$D$47)^(H$2-1) -> -16583 | I13: =-Parametres!$D$117*(1+Parametres!$D$47)^(I$2-1) -> -16583 | ... AK13: =-Parametres!$D$117*(1+Parametres!$D$47)^(AK$2-1) -> -19342.411
A14: Object Storage | B14: =-Parametres!$D$118*(1+Parametres!$D$47)^(B$2-1) -> -30000 | C14: =-Parametres!$D$118*(1+Parametres!$D$47)^(C$2-1) -> -30000 | D14: =-Parametres!$D$118*(1+Parametres!$D$47)^(D$2-1) -> -30000 | E14: =-Parametres!$D$118*(1+Parametres!$D$47)^(E$2-1) -> -30000 | F14: =-Parametres!$D$118*(1+Parametres!$D$47)^(F$2-1) -> -30000 | G14: =-Parametres!$D$118*(1+Parametres!$D$47)^(G$2-1) -> -30000 | H14: =-Parametres!$D$118*(1+Parametres!$D$47)^(H$2-1) -> -30000 | I14: =-Parametres!$D$118*(1+Parametres!$D$47)^(I$2-1) -> -30000 | ... AK14: =-Parametres!$D$118*(1+Parametres!$D$47)^(AK$2-1) -> -34992
A15: Modération | B15: =-Parametres!$D$119*(1+Parametres!$D$47)^(B$2-1) -> -10000 | C15: =-Parametres!$D$119*(1+Parametres!$D$47)^(C$2-1) -> -10000 | D15: =-Parametres!$D$119*(1+Parametres!$D$47)^(D$2-1) -> -10000 | E15: =-Parametres!$D$119*(1+Parametres!$D$47)^(E$2-1) -> -10000 | F15: =-Parametres!$D$119*(1+Parametres!$D$47)^(F$2-1) -> -10000 | G15: =-Parametres!$D$119*(1+Parametres!$D$47)^(G$2-1) -> -10000 | H15: =-Parametres!$D$119*(1+Parametres!$D$47)^(H$2-1) -> -10000 | I15: =-Parametres!$D$119*(1+Parametres!$D$47)^(I$2-1) -> -10000 | ... AK15: =-Parametres!$D$119*(1+Parametres!$D$47)^(AK$2-1) -> -11664
A16: Marketing (accompagnement fixe + budget publicité par année) | B16: =-(Parametres!$D$120*(1+Parametres!$D$47)^(B$2-1)+'Plan ventes'!B6) -> -500000 | C16: =-(Parametres!$D$120*(1+Parametres!$D$47)^(C$2-1)+'Plan ventes'!C6) -> -500000 | D16: =-(Parametres!$D$120*(1+Parametres!$D$47)^(D$2-1)+'Plan ventes'!D6) -> -500000 | E16: =-(Parametres!$D$120*(1+Parametres!$D$47)^(E$2-1)+'Plan ventes'!E6) -> -500000 | F16: =-(Parametres!$D$120*(1+Parametres!$D$47)^(F$2-1)+'Plan ventes'!F6) -> -500000 | G16: =-(Parametres!$D$120*(1+Parametres!$D$47)^(G$2-1)+'Plan ventes'!G6) -> -500000 | H16: =-(Parametres!$D$120*(1+Parametres!$D$47)^(H$2-1)+'Plan ventes'!H6) -> -500000 | I16: =-(Parametres!$D$120*(1+Parametres!$D$47)^(I$2-1)+'Plan ventes'!I6) -> -500000 | ... AK16: =-(Parametres!$D$120*(1+Parametres!$D$47)^(AK$2-1)+'Plan ventes'!AK6) -> -716640
A17: Total OPEX | B17: =SUM(B11:B16) -> -2805583 | C17: =SUM(C11:C16) -> -2805583 | D17: =SUM(D11:D16) -> -2805583 | E17: =SUM(E11:E16) -> -2805583 | F17: =SUM(F11:F16) -> -2805583 | G17: =SUM(G11:G16) -> -2805583 | H17: =SUM(H11:H16) -> -2805583 | I17: =SUM(I11:I16) -> -2805583 | ... AK17: =SUM(AK11:AK16) -> -3956412.8
A18: EBITDA | B18: =B8+B17 -> -1829596.5 | C18: =C8+C17 -> -1645726.6 | D18: =D8+D17 -> -1588368 | E18: =E8+E17 -> -1528610.1 | F18: =F8+F17 -> -1466321.7 | G18: =G8+G17 -> -1401365.9 | H18: =H8+H17 -> -1274475.5 | I18: =I8+I17 -> -1202564.8 | ... AK18: =AK8+AK17 -> 1726187
A19: % EBITDA | B19: =IF(B5=0,0,B18/B5) -> -1.3118209 | C19: =IF(C5=0,0,C18/C5) -> -1.1307817 | D19: =IF(D5=0,0,D18/D5) -> -1.0460407 | E19: =IF(E5=0,0,E18/E5) -> -0.965011 | F19: =IF(F5=0,0,F18/F5) -> -0.88746856 | G19: =IF(G5=0,0,G18/G5) -> -0.81321033 | H19: =IF(H5=0,0,H18/H5) -> -0.68656689 | I19: =IF(I5=0,0,I18/I5) -> -0.6216436 | ... AK19: =IF(AK5=0,0,AK18/AK5) -> 0.27177014
A20: Dotations aux amortissements | B20: =-Amortissements!$H$6 -> -81666.667 | C20: =-Amortissements!$H$6 -> -81666.667 | D20: =-Amortissements!$H$6 -> -81666.667 | E20: =-Amortissements!$H$6 -> -81666.667 | F20: =-Amortissements!$H$6 -> -81666.667 | G20: =-Amortissements!$H$6 -> -81666.667 | H20: =-Amortissements!$H$6 -> -81666.667 | I20: =-Amortissements!$H$6 -> -81666.667 | ... AK20: =-Amortissements!$H$6 -> -81666.667
A21: RÉSULTAT OPÉRATIONNEL (EBIT) | B21: =B18+B20 -> -1911263.2 | C21: =C18+C20 -> -1727393.3 | D21: =D18+D20 -> -1670034.7 | E21: =E18+E20 -> -1610276.7 | F21: =F18+F20 -> -1547988.4 | G21: =G18+G20 -> -1483032.6 | H21: =H18+H20 -> -1356142.2 | I21: =I18+I20 -> -1284231.4 | ... AK21: =AK18+AK20 -> 1644520.3
A22: Charges financières (intérêts d'emprunt) | B22: =-Financement!C32 -> -322562.31 | C22: =-Financement!D32 -> -318285.66 | D22: =-Financement!E32 -> -313976.94 | E22: =-Financement!F32 -> -309635.9 | F22: =-Financement!G32 -> -305262.31 | G22: =-Financement!H32 -> -300855.91 | H22: =-Financement!I32 -> -296416.47 | I22: =-Financement!J32 -> -291943.73 | ... AK22: =-Financement!AL32 -> -152121.67
A23: RÉSULTAT AVANT IMPÔT | B23: =B21+B22 -> -2233825.5 | C23: =C21+C22 -> -2045678.9 | D23: =D21+D22 -> -1984011.6 | E23: =E21+E22 -> -1919912.6 | F23: =F21+F22 -> -1853250.7 | G23: =G21+G22 -> -1783888.5 | H23: =H21+H22 -> -1652558.7 | I23: =I21+I22 -> -1576175.2 | ... AK23: =AK21+AK22 -> 1492398.6
A24: Impôt (IS synthétique 5 % du CA ou IR 20 %) — comptabilisé au mois 12 de chaque exercice | B24: =0 -> 0 | C24: =0 -> 0 | D24: =0 -> 0 | E24: =0 -> 0 | F24: =0 -> 0 | G24: =0 -> 0 | H24: =0 -> 0 | I24: =0 -> 0 | ... L24: =0 -> 0 | M24: =-$B$34 -> -1085331 | N24: =0 -> 0 | O24: =0 -> 0 | P24: =0 -> 0 | Q24: =0 -> 0 | R24: =0 -> 0 | S24: =0 -> 0 | T24: =0 -> 0 | U24: =0 -> 0 | ... X24: =0 -> 0 | Y24: =-$C$34 -> -1904351.2 | Z24: =0 -> 0 | AA24: =0 -> 0 | AB24: =0 -> 0 | AC24: =0 -> 0 | AD24: =0 -> 0 | AE24: =0 -> 0 | AF24: =0 -> 0 | AG24: =0 -> 0 | ... AJ24: =0 -> 0 | AK24: =-$D$34 -> -3172760.8
A25: RÉSULTAT NET | B25: =B23+B24 -> -2233825.5 | C25: =C23+C24 -> -2045678.9 | D25: =D23+D24 -> -1984011.6 | E25: =E23+E24 -> -1919912.6 | F25: =F23+F24 -> -1853250.7 | G25: =G23+G24 -> -1783888.5 | H25: =H23+H24 -> -1652558.7 | I25: =I23+I24 -> -1576175.2 | ... AK25: =AK23+AK24 -> -1680362.2
A26: % marge nette | B26: =IF(B5=0,0,B25/B5) -> -1.6016531 | C26: =IF(C5=0,0,C25/C5) -> -1.4055897 | D26: =IF(D5=0,0,D25/D5) -> -1.3065971 | E26: =IF(E5=0,0,E25/E5) -> -1.2120402 | F26: =IF(F5=0,0,F25/F5) -> -1.1216513 | G26: =IF(G5=0,0,G25/G5) -> -1.0351876 | H26: =IF(H5=0,0,H25/H5) -> -0.89024233 | I26: =IF(I5=0,0,I25/I5) -> -0.81477459 | ... AK26: =IF(AK5=0,0,AK25/AK5) -> -0.26455551
A28: RÉCAPITULATIF ANNUEL ET CALCUL DE L'IMPÔT (Madagascar, LF 2026)
B29: Année 1 | C29: Année 2 | D29: Année 3
A30: Chiffre d'affaires annuel | B30: =SUMIF($B$2:$AK$2,1,$B$5:$AK$5) -> 21706621 | C30: =SUMIF($B$2:$AK$2,2,$B$5:$AK$5) -> 38087024 | D30: =SUMIF($B$2:$AK$2,3,$B$5:$AK$5) -> 63455216
A31: EBITDA annuel | B31: =SUMIF($B$2:$AK$2,1,$B$18:$AK$18) -> -15962797 | C31: =SUMIF($B$2:$AK$2,2,$B$18:$AK$18) -> -4181951.1 | D31: =SUMIF($B$2:$AK$2,3,$B$18:$AK$18) -> 8893982.1
A32: Résultat avant impôt annuel | B32: =SUMIF($B$2:$AK$2,1,$B$23:$AK$23) -> -20524109 | C32: =SUMIF($B$2:$AK$2,2,$B$23:$AK$23) -> -8074225.9 | D32: =SUMIF($B$2:$AK$2,3,$B$23:$AK$23) -> 5733504.8
A33: Déficits antérieurs reportables (régime réel) | B33: 0 | C33: =MIN(0,B32) -> -20524109 | D33: =MIN(0,B32+C32) -> -28598335
A34: Impôt dû (IS 5 % du CA si CA < seuil, sinon IR 20 %) | B34: =IF(B30<Parametres!$D$150,Parametres!$D$151*B30,MAX(Parametres!$D$152*MAX(0,B32+B33),Parametres!$D$153+Parametres!$D$154*B30)) -> 1085331 | C34: =IF(C30<Parametres!$D$150,Parametres!$D$151*C30,MAX(Parametres!$D$152*MAX(0,C32+C33),Parametres!$D$153+Parametres!$D$154*C30)) -> 1904351.2 | D34: =IF(D30<Parametres!$D$150,Parametres!$D$151*D30,MAX(Parametres!$D$152*MAX(0,D32+D33),Parametres!$D$153+Parametres!$D$154*D30)) -> 3172760.8
A35: Résultat net annuel | B35: =B32-B34 -> -21609440 | C35: =C32-C34 -> -9978577.1 | D35: =D32-D34 -> 2560744
A37: Simplifications documentées : impôt comptabilisé et payé au mois 12 de chaque exercice ; report des déficits appliqué uniquement au régime réel (IR).

Sheet Bilan
A1: BILAN SIMPLIFIÉ — actif = passif (MGA) — M0 setup + M1–M36
A2: Année | C2: 0 | D2: =INT((D3-1)/12)+1 -> 1 | E2: =INT((E3-1)/12)+1 -> 1 | F2: =INT((F3-1)/12)+1 -> 1 | G2: =INT((G3-1)/12)+1 -> 1 | H2: =INT((H3-1)/12)+1 -> 1 | I2: =INT((I3-1)/12)+1 -> 1 | J2: =INT((J3-1)/12)+1 -> 1 | K2: =INT((K3-1)/12)+1 -> 1 | ... AM2: =INT((AM3-1)/12)+1 -> 3
A3: Mois | C3: 0 | D3: 1 | E3: 2 | F3: 3 | G3: 4 | H3: 5 | I3: 6 | J3: 7 | K3: 8 | L3: 9 | M3: 10 | N3: 11 | O3: 12 | P3: 13 | Q3: 14 | R3: 15 | S3: 16 | T3: 17 | U3: 18 | V3: 19 | W3: 20 | X3: 21 | Y3: 22 | Z3: 23 | AA3: 24 | AB3: 25 | AC3: 26 | AD3: 27 | AE3: 28 | AF3: 29 | AG3: 30 | AH3: 31 | AI3: 32 | AJ3: 33 | AK3: 34 | AL3: 35 | AM3: 36
A5: ACTIF
A6: Immobilisations brutes (CAPEX) | C6: =Financement!B4 -> 4900000 | D6: =Financement!$B$4 -> 4900000 | E6: =Financement!$B$4 -> 4900000 | F6: =Financement!$B$4 -> 4900000 | G6: =Financement!$B$4 -> 4900000 | H6: =Financement!$B$4 -> 4900000 | I6: =Financement!$B$4 -> 4900000 | J6: =Financement!$B$4 -> 4900000 | K6: =Financement!$B$4 -> 4900000 | ... AM6: =Financement!$B$4 -> 4900000
A7: Amortissements cumulés | C7: 0 | D7: =-Amortissements!$H$6*D$3 -> -81666.667 | E7: =-Amortissements!$H$6*E$3 -> -163333.33 | F7: =-Amortissements!$H$6*F$3 -> -245000 | G7: =-Amortissements!$H$6*G$3 -> -326666.67 | H7: =-Amortissements!$H$6*H$3 -> -408333.33 | I7: =-Amortissements!$H$6*I$3 -> -490000 | J7: =-Amortissements!$H$6*J$3 -> -571666.67 | K7: =-Amortissements!$H$6*K$3 -> -653333.33 | ... AM7: =-Amortissements!$H$6*AM$3 -> -2940000
A8: Immobilisations nettes (VNC) | C8: =C6+C7 -> 4900000 | D8: =D6+D7 -> 4818333.3 | E8: =E6+E7 -> 4736666.7 | F8: =F6+F7 -> 4655000 | G8: =G6+G7 -> 4573333.3 | H8: =H6+H7 -> 4491666.7 | I8: =I6+I7 -> 4410000 | J8: =J6+J7 -> 4328333.3 | ... AM8: =AM6+AM7 -> 1960000
A9: Trésorerie | C9: =Tresorerie!C25 -> 47108307 | D9: =Tresorerie!D25 -> 44385929 | E9: =Tresorerie!E25 -> 41847421 | F9: =Tresorerie!F25 -> 39366271 | G9: =Tresorerie!G25 -> 36944879 | H9: =Tresorerie!H25 -> 34585776 | I9: =Tresorerie!I25 -> 32291628 | J9: =Tresorerie!J25 -> 30124371 | ... AM9: =Tresorerie!AM25 -> -2445043.6
A10: TOTAL ACTIF | C10: =C8+C9 -> 52008307 | D10: =D8+D9 -> 49204263 | E10: =E8+E9 -> 46584088 | F10: =F8+F9 -> 44021271 | G10: =G8+G9 -> 41518213 | H10: =H8+H9 -> 39077443 | I10: =I8+I9 -> 36701628 | J10: =J8+J9 -> 34452704 | ... AM10: =AM8+AM9 -> -485043.63
A12: PASSIF ET CAPITAUX PROPRES
A13: Emprunt restant dû | C13: =Financement!B23 -> 43008307 | D13: =IF(D$3>Financement!$B$25,0,Financement!C34) -> 42438088 | E13: =IF(E$3>Financement!$B$25,0,Financement!D34) -> 41863592 | F13: =IF(F$3>Financement!$B$25,0,Financement!E34) -> 41284787 | G13: =IF(G$3>Financement!$B$25,0,Financement!F34) -> 40701641 | H13: =IF(H$3>Financement!$B$25,0,Financement!G34) -> 40114122 | I13: =IF(I$3>Financement!$B$25,0,Financement!H34) -> 39522196 | J13: =IF(J$3>Financement!$B$25,0,Financement!I34) -> 38925831 | K13: =IF(K$3>Financement!$B$25,0,Financement!J34) -> 38324993 | ... AM13: =IF(AM$3>Financement!$B$25,0,Financement!AL34) -> 19542230
A14: Capitaux propres — apport | C14: =Financement!B14 -> 9000000 | D14: =Financement!$B$14 -> 9000000 | E14: =Financement!$B$14 -> 9000000 | F14: =Financement!$B$14 -> 9000000 | G14: =Financement!$B$14 -> 9000000 | H14: =Financement!$B$14 -> 9000000 | I14: =Financement!$B$14 -> 9000000 | J14: =Financement!$B$14 -> 9000000 | K14: =Financement!$B$14 -> 9000000 | ... AM14: =Financement!$B$14 -> 9000000
A15: Capitaux propres — résultat net cumulé | C15: 0 | D15: =SUM('P&L'!B25:B25) -> -2233825.5 | E15: =SUM('P&L'!B25:C25) -> -4279504.4 | F15: =SUM('P&L'!B25:D25) -> -6263516.1 | G15: =SUM('P&L'!B25:E25) -> -8183428.7 | H15: =SUM('P&L'!B25:F25) -> -10036679 | I15: =SUM('P&L'!B25:G25) -> -11820568 | J15: =SUM('P&L'!B25:H25) -> -13473127 | K15: =SUM('P&L'!B25:I25) -> -15049302 | L15: =SUM('P&L'!B25:J25) -> -16545917 | M15: =SUM('P&L'!B25:K25) -> -17959631 | N15: =SUM('P&L'!B25:L25) -> -19286928 | O15: =SUM('P&L'!B25:M25) -> -21609440 | P15: =SUM('P&L'!B25:N25) -> -22884678 | Q15: =SUM('P&L'!B25:O25) -> -24064400 | R15: =SUM('P&L'!B25:P25) -> -25144561 | S15: =SUM('P&L'!B25:Q25) -> -26121285 | T15: =SUM('P&L'!B25:R25) -> -26990516 | U15: =SUM('P&L'!B25:S25) -> -27748015 | V15: =SUM('P&L'!B25:T25) -> -28389347 | W15: =SUM('P&L'!B25:U25) -> -28909875 | X15: =SUM('P&L'!B25:V25) -> -29304754 | Y15: =SUM('P&L'!B25:W25) -> -29568916 | Z15: =SUM('P&L'!B25:X25) -> -29697065 | AA15: =SUM('P&L'!B25:Y25) -> -31588017 | AB15: =SUM('P&L'!B25:Z25) -> -32015401 | AC15: =SUM('P&L'!B25:AA25) -> -32309106 | AD15: =SUM('P&L'!B25:AB25) -> -32446509 | AE15: =SUM('P&L'!B25:AC25) -> -32423190 | AF15: =SUM('P&L'!B25:AD25) -> -32234540 | AG15: =SUM('P&L'!B25:AE25) -> -31875751 | AH15: =SUM('P&L'!B25:AF25) -> -31341814 | AI15: =SUM('P&L'!B25:AG25) -> -30627509 | AJ15: =SUM('P&L'!B25:AH25) -> -29727401 | AK15: =SUM('P&L'!B25:AI25) -> -28635832 | AL15: =SUM('P&L'!B25:AJ25) -> -27346911 | AM15: =SUM('P&L'!B25:AK25) -> -29027273
A16: TOTAL PASSIF + CP | C16: =C13+C14+C15 -> 52008307 | D16: =D13+D14+D15 -> 49204263 | E16: =E13+E14+E15 -> 46584088 | F16: =F13+F14+F15 -> 44021271 | G16: =G13+G14+G15 -> 41518213 | H16: =H13+H14+H15 -> 39077443 | I16: =I13+I14+I15 -> 36701628 | J16: =J13+J14+J15 -> 34452704 | ... AM16: =AM13+AM14+AM15 -> -485043.63
A18: Contrôle (actif − passif, doit = 0) | C18: =C10-C16 -> 0 | D18: =D10-D16 -> 0 | E18: =E10-E16 -> 0 | F18: =F10-F16 -> 0 | G18: =G10-G16 -> 0 | H18: =H10-H16 -> 0 | I18: =I10-I16 -> 0 | J18: =J10-J16 -> 0 | ... AM18: =AM10-AM16 -> -1.1175871e-08
A19: OK si abs(contrôle) < 1 Ar | C19: =IF(ABS(C18)<1,"OK","ÉCART") -> OK | D19: =IF(ABS(D18)<1,"OK","ÉCART") -> OK | E19: =IF(ABS(E18)<1,"OK","ÉCART") -> OK | F19: =IF(ABS(F18)<1,"OK","ÉCART") -> OK | G19: =IF(ABS(G18)<1,"OK","ÉCART") -> OK | H19: =IF(ABS(H18)<1,"OK","ÉCART") -> OK | I19: =IF(ABS(I18)<1,"OK","ÉCART") -> OK | J19: =IF(ABS(J18)<1,"OK","ÉCART") -> OK | ... AM19: =IF(ABS(AM18)<1,"OK","ÉCART") -> OK
A21: Simplifications : pas de créances clients (encaissement Mobile Money), impôt payé au mois 12 de chaque exercice (déjà dans le RN et la trésorerie), pas de BFR stocks. Identité : VNC + caisse = dette + apport + RN cumulé.

Sheet Amortissements
A1: AMORTISSEMENTS — linéaires, IFRS (IAS 16 corporelles / IAS 38 incorporelles)
A3: Immobilisation | B3: Norme IFRS | C3: Qté | D3: PU (Ar) | E3: Valeur brute | F3: Durée (ans) | G3: Amort. annuel | H3: Amort. mensuel | I3: Année 1 | J3: Année 2 | K3: Année 3 | L3: Cumul 3 ans | M3: VNC fin A3
A4: Ordinateur portable | B4: IAS 16 — corporelle | C4: =Parametres!$B$133 -> 1 | D4: =Parametres!$C$133 -> 900000 | E4: =Parametres!$D$133 -> 900000 | F4: =Parametres!$E$133 -> 5 | G4: =E4/F4 -> 180000 | H4: =G4/12 -> 15000 | I4: =G4 -> 180000 | J4: =G4 -> 180000 | K4: =G4 -> 180000 | L4: =SUM(I4:K4) -> 540000 | M4: =E4-L4 -> 360000
A5: Design graphique UI/UX | B5: IAS 38 — incorporelle | C5: =Parametres!$B$134 -> 1 | D5: =Parametres!$C$134 -> 4000000 | E5: =Parametres!$D$134 -> 4000000 | F5: =Parametres!$E$134 -> 5 | G5: =E5/F5 -> 800000 | H5: =G5/12 -> 66666.667 | I5: =G5 -> 800000 | J5: =G5 -> 800000 | K5: =G5 -> 800000 | L5: =SUM(I5:K5) -> 2400000 | M5: =E5-L5 -> 1600000
A6: TOTAL | E6: =SUM(E4:E5) -> 4900000 | G6: =SUM(G4:G5) -> 980000 | H6: =SUM(H4:H5) -> 81666.667 | I6: =SUM(I4:I5) -> 980000 | J6: =SUM(J4:J5) -> 980000 | K6: =SUM(K4:K5) -> 980000 | L6: =SUM(L4:L5) -> 2940000 | M6: =SUM(M4:M5) -> 1960000
A8: Hypothèse : mise en service au mois 1 ; amortissement linéaire sans valeur résiduelle (IAS 16.50 / IAS 38.97). VNC = valeur nette comptable.

Sheet Financement
A1: FINANCEMENT — besoin initial, plan de financement (Ask), emprunt et validation sur 3 ans
A3: BESOIN DE FINANCEMENT INITIAL
A4: CAPEX (investissements, choc stress inclus) | B4: =Parametres!$D$135*(1+IF(Parametres!$B$158=1,Parametres!$B$162,0)) -> 4900000
A5: Charges fixes mensuelles année 1 (OPEX chargés + budget publicité A1) | B5: =Parametres!$D$121+Parametres!$D$63 -> 2805583 | C5: Parametres sections 13 et 9 — multiplicateur scénario et choc stress inclus.
A6: Coûts variables du mois 1 | B6: =-'P&L'!B7 -> 418713.54 | C6: Mobile Money, SMS, support, vérification, litiges du premier mois.
A7: Nombre de mois de démarrage couverts | B7: =Parametres!$D$140 -> 12
A8: Besoin de démarrage (N mois × (charges fixes + coûts variables M1)) | B8: =B7*(B5+B6) -> 38691558
A9: Nombre de mois de charges fixes en sécurité | B9: =Parametres!$D$141 -> 3
A10: Trésorerie de sécurité (N mois × charges fixes) — cible de la validation | B10: =B9*B5 -> 8416749
A11: TOTAL BESOIN DE FINANCEMENT | B11: =B4+B8+B10 -> 52008307
A13: PLAN DE FINANCEMENT & ASK (demande de fonds)
A14: Apport en fonds propres (fondateurs) | B14: =Parametres!$D$139 -> 9000000
A15: Emprunt (mécanique inchangée : besoin non couvert par l'apport, porté en dette dans la trésorerie) | B15: =MAX(B11-B14,0) -> 43008307
A16: TOTAL RESSOURCES (= besoin) | B16: =B14+B15 -> 52008307
A17: Part du financement externe dans le total | B17: =IF(B16=0,0,B15/B16) -> 0.82695072
A18: ASK — financement externe recherché auprès d'investisseurs / bailleurs (besoin − apport) | B18: =B11-B14 -> 43008307 | C18: Montant à présenter aux financeurs. Ventilation indicative ci-dessous ; la trésorerie modélise l'ensemble en emprunt.
A19: dont visé en equity / quasi-fonds propres (investisseurs) — indicatif | B19: =B18*Parametres!$D$145 -> 12902492 | C19: Part paramétrable (Parametres section 16).
A20: dont visé en dette (banques / bailleurs) — indicatif | B20: =B18-B19 -> 30105815
A22: EMPRUNT — CONDITIONS
A23: Montant emprunté | B23: =B15 -> 43008307
A24: Taux annuel | B24: =Parametres!$D$143 -> 0.09
A25: Durée (mois) | B25: =Parametres!$D$144 -> 60
A26: Mensualité constante (annuités) | B26: =IF(B23=0,0,-PMT(B24/12,B25,B23)) -> 892781.72
A27: Coût total des intérêts sur la durée | B27: =B32 -> 8674064.2 | C27: Intérêts → P&L ligne 22 et Trésorerie ligne 9 ; capital → Trésorerie ligne 20 ; dette restante → Bilan ligne 13.
A29: TABLEAU D'AMORTISSEMENT DE L'EMPRUNT (mensuel)
A30: Mois | B30: TOTAL | C30: 1 | D30: 2 | E30: 3 | F30: 4 | G30: 5 | H30: 6 | I30: 7 | J30: 8 | K30: 9 | L30: 10 | M30: 11 | N30: 12 | O30: 13 | P30: 14 | Q30: 15 | R30: 16 | S30: 17 | T30: 18 | U30: 19 | V30: 20 | W30: 21 | X30: 22 | Y30: 23 | Z30: 24 | AA30: 25 | AB30: 26 | AC30: 27 | AD30: 28 | AE30: 29 | AF30: 30 | AG30: 31 | AH30: 32 | AI30: 33 | AJ30: 34 | AK30: 35 | AL30: 36
A31: Mensualité | B31: =SUM(C31:AL31) -> 32140142 | C31: =IF(C$30>$B$25,0,-PMT($B$24/12,$B$25,$B$23)) -> 892781.72 | D31: =IF(D$30>$B$25,0,-PMT($B$24/12,$B$25,$B$23)) -> 892781.72 | E31: =IF(E$30>$B$25,0,-PMT($B$24/12,$B$25,$B$23)) -> 892781.72 | F31: =IF(F$30>$B$25,0,-PMT($B$24/12,$B$25,$B$23)) -> 892781.72 | G31: =IF(G$30>$B$25,0,-PMT($B$24/12,$B$25,$B$23)) -> 892781.72 | H31: =IF(H$30>$B$25,0,-PMT($B$24/12,$B$25,$B$23)) -> 892781.72 | I31: =IF(I$30>$B$25,0,-PMT($B$24/12,$B$25,$B$23)) -> 892781.72 | J31: =IF(J$30>$B$25,0,-PMT($B$24/12,$B$25,$B$23)) -> 892781.72 | ... AL31: =IF(AL$30>$B$25,0,-PMT($B$24/12,$B$25,$B$23)) -> 892781.72
A32: Intérêts | B32: =SUM(C32:AL32) -> 8674064.2 | C32: =IF(C$30>$B$25,0,-IPMT($B$24/12,C$30,$B$25,$B$23)) -> 322562.31 | D32: =IF(D$30>$B$25,0,-IPMT($B$24/12,D$30,$B$25,$B$23)) -> 318285.66 | E32: =IF(E$30>$B$25,0,-IPMT($B$24/12,E$30,$B$25,$B$23)) -> 313976.94 | F32: =IF(F$30>$B$25,0,-IPMT($B$24/12,F$30,$B$25,$B$23)) -> 309635.9 | G32: =IF(G$30>$B$25,0,-IPMT($B$24/12,G$30,$B$25,$B$23)) -> 305262.31 | H32: =IF(H$30>$B$25,0,-IPMT($B$24/12,H$30,$B$25,$B$23)) -> 300855.91 | I32: =IF(I$30>$B$25,0,-IPMT($B$24/12,I$30,$B$25,$B$23)) -> 296416.47 | J32: =IF(J$30>$B$25,0,-IPMT($B$24/12,J$30,$B$25,$B$23)) -> 291943.73 | ... AL32: =IF(AL$30>$B$25,0,-IPMT($B$24/12,AL$30,$B$25,$B$23)) -> 152121.67
A33: Capital remboursé | B33: =SUM(C33:AL33) -> 23466078 | C33: =IF(C$30>$B$25,0,-PPMT($B$24/12,C$30,$B$25,$B$23)) -> 570219.42 | D33: =IF(D$30>$B$25,0,-PPMT($B$24/12,D$30,$B$25,$B$23)) -> 574496.06 | E33: =IF(E$30>$B$25,0,-PPMT($B$24/12,E$30,$B$25,$B$23)) -> 578804.78 | F33: =IF(F$30>$B$25,0,-PPMT($B$24/12,F$30,$B$25,$B$23)) -> 583145.82 | G33: =IF(G$30>$B$25,0,-PPMT($B$24/12,G$30,$B$25,$B$23)) -> 587519.41 | H33: =IF(H$30>$B$25,0,-PPMT($B$24/12,H$30,$B$25,$B$23)) -> 591925.81 | I33: =IF(I$30>$B$25,0,-PPMT($B$24/12,I$30,$B$25,$B$23)) -> 596365.25 | J33: =IF(J$30>$B$25,0,-PPMT($B$24/12,J$30,$B$25,$B$23)) -> 600837.99 | ... AL33: =IF(AL$30>$B$25,0,-PPMT($B$24/12,AL$30,$B$25,$B$23)) -> 740660.05
A34: Capital restant dû | C34: =$B$23-C33 -> 42438088 | D34: =C34-D33 -> 41863592 | E34: =D34-E33 -> 41284787 | F34: =E34-F33 -> 40701641 | G34: =F34-G33 -> 40114122 | H34: =G34-H33 -> 39522196 | I34: =H34-I33 -> 38925831 | J34: =I34-J33 -> 38324993 | K34: =J34-K33 -> 37719649 | ... AL34: =AK34-AL33 -> 19542230
A36: VALIDATION 3 ANS — la trésorerie reste-t-elle au-dessus du matelas de sécurité sur M0–M36 ?
A37: Pic de besoin cumulé de trésorerie AVANT financement (flux op. hors intérêts + CAPEX) | B37: =-MIN(B48:AL48) -> 28176175 | C37: Point bas du cumul des flux (ligne 48) : montant à financer pour ne jamais être à zéro, hors coût de la dette.
A38: Financement minimal pour conserver le matelas de sécurité (pic + sécurité, hors service de la dette) | B38: =B37+B10 -> 36592924
A39: Trésorerie minimale sur 36 mois APRÈS financement et service de la dette | B39: =MIN(Tresorerie!D25:AM25) -> -2445043.6
A40: Couverture du matelas de sécurité (cible = ligne 10) | B40: =IF(B39>=B10,"OK — trésorerie ≥ "&B9&" mois de charges fixes sur toute la période","INSUFFISANT — augmenter apport, mois financés ou durée") -> INSUFFISANT — augmenter apport, mois financés ou durée
A41: Financement externe minimum indicatif pour atteindre la cible (itération suivante, hors intérêts additionnels) | B41: =B15+MAX(0,B10-B39) -> 53870100
A42: Référence V2.3 — apport 36,7 M Ar calé à la main pour un plancher de 1 M | B42: =Parametres!$D$146 -> 36700000
A43: Écart référence 36,7 M vs financement minimal (positif = référence surdimensionnée) | B43: =B42-B38 -> 107075.78
A44: Capital restant dû à la fin du mois 36 (emprunt plus long que l'horizon du modèle) | B44: =AL34 -> 19542230 | C44: Nul si la durée ≤ 36 mois.
A45: Trésorerie fin M36 nette de la dette restante | B45: =Tresorerie!AM25-B44 -> -21987273
A48: Cumul flux opérationnels (hors intérêts) + CAPEX, avant financement — M0 (col. B) → M36 (col. AL) | B48: =(SUM(Tresorerie!C6:C8)+Tresorerie!C10+Tresorerie!C15) -> -4900000 | C48: =B48+(SUM(Tresorerie!D6:D8)+Tresorerie!D10+Tresorerie!D15) -> -6729596.5 | D48: =C48+(SUM(Tresorerie!E6:E8)+Tresorerie!E10+Tresorerie!E15) -> -8375323.1 | E48: =D48+(SUM(Tresorerie!F6:F8)+Tresorerie!F10+Tresorerie!F15) -> -9963691.2 | F48: =E48+(SUM(Tresorerie!G6:G8)+Tresorerie!G10+Tresorerie!G15) -> -11492301 | G48: =F48+(SUM(Tresorerie!H6:H8)+Tresorerie!H10+Tresorerie!H15) -> -12958623 | H48: =G48+(SUM(Tresorerie!I6:I8)+Tresorerie!I10+Tresorerie!I15) -> -14359989 | I48: =H48+(SUM(Tresorerie!J6:J8)+Tresorerie!J10+Tresorerie!J15) -> -15634464 | J48: =I48+(SUM(Tresorerie!K6:K8)+Tresorerie!K10+Tresorerie!K15) -> -16837029 | ... AL48: =AK48+(SUM(Tresorerie!AM6:AM8)+Tresorerie!AM10+Tresorerie!AM15) -> -22313209

Sheet Tresorerie
A1: FLUX DE TRÉSORERIE (IAS 7, méthode directe) — M0 (setup) + M1–M36
A2: Année | D2: ='P&L'!B2 -> 1 | E2: ='P&L'!C2 -> 1 | F2: ='P&L'!D2 -> 1 | G2: ='P&L'!E2 -> 1 | H2: ='P&L'!F2 -> 1 | I2: ='P&L'!G2 -> 1 | J2: ='P&L'!H2 -> 1 | K2: ='P&L'!I2 -> 1 | ... AM2: ='P&L'!AK2 -> 3
A3: Mois | C3: 0 | D3: 1 | E3: 2 | F3: 3 | G3: 4 | H3: 5 | I3: 6 | J3: 7 | K3: 8 | L3: 9 | M3: 10 | N3: 11 | O3: 12 | P3: 13 | Q3: 14 | R3: 15 | S3: 16 | T3: 17 | U3: 18 | V3: 19 | W3: 20 | X3: 21 | Y3: 22 | Z3: 23 | AA3: 24 | AB3: 25 | AC3: 26 | AD3: 27 | AE3: 28 | AF3: 29 | AG3: 30 | AH3: 31 | AI3: 32 | AJ3: 33 | AK3: 34 | AL3: 35 | AM3: 36
A5: FLUX DE TRÉSORERIE OPÉRATIONNELS
A6: Encaissements clients (CA) | D6: =IF(Parametres!$B$158=1,IF(D$3-Parametres!$B$165>=1,INDEX('P&L'!$B$5:$AK$5,1,D$3-Parametres!$B$165),0)*(1-Parametres!$B$163),'P&L'!B5) -> 1394700 | E6: =IF(Parametres!$B$158=1,IF(E$3-Parametres!$B$165>=1,INDEX('P&L'!$B$5:$AK$5,1,E$3-Parametres!$B$165),0)*(1-Parametres!$B$163),'P&L'!C5) -> 1455388.4 | F6: =IF(Parametres!$B$158=1,IF(F$3-Parametres!$B$165>=1,INDEX('P&L'!$B$5:$AK$5,1,F$3-Parametres!$B$165),0)*(1-Parametres!$B$163),'P&L'!D5) -> 1518457.2 | G6: =IF(Parametres!$B$158=1,IF(G$3-Parametres!$B$165>=1,INDEX('P&L'!$B$5:$AK$5,1,G$3-Parametres!$B$165),0)*(1-Parametres!$B$163),'P&L'!E5) -> 1584033.8 | H6: =IF(Parametres!$B$158=1,IF(H$3-Parametres!$B$165>=1,INDEX('P&L'!$B$5:$AK$5,1,H$3-Parametres!$B$165),0)*(1-Parametres!$B$163),'P&L'!F5) -> 1652252 | I6: =IF(Parametres!$B$158=1,IF(I$3-Parametres!$B$165>=1,INDEX('P&L'!$B$5:$AK$5,1,I$3-Parametres!$B$165),0)*(1-Parametres!$B$163),'P&L'!G5) -> 1723251.5 | J6: =IF(Parametres!$B$158=1,IF(J$3-Parametres!$B$165>=1,INDEX('P&L'!$B$5:$AK$5,1,J$3-Parametres!$B$165),0)*(1-Parametres!$B$163),'P&L'!H5) -> 1856302 | K6: =IF(Parametres!$B$158=1,IF(K$3-Parametres!$B$165>=1,INDEX('P&L'!$B$5:$AK$5,1,K$3-Parametres!$B$165),0)*(1-Parametres!$B$163),'P&L'!I5) -> 1934492.3 | ... AM6: =IF(Parametres!$B$158=1,IF(AM$3-Parametres!$B$165>=1,INDEX('P&L'!$B$5:$AK$5,1,AM$3-Parametres!$B$165),0)*(1-Parametres!$B$163),'P&L'!AK5) -> 6351643.2
A7: Décaissements coûts variables | D7: ='P&L'!B7 -> -418713.54 | E7: ='P&L'!C7 -> -295532.03 | F7: ='P&L'!D7 -> -301242.19 | G7: ='P&L'!E7 -> -307060.89 | H7: ='P&L'!F7 -> -312990.73 | I7: ='P&L'!G7 -> -319034.37 | J7: ='P&L'!H7 -> -325194.55 | K7: ='P&L'!I7 -> -331474.06 | ... AM7: ='P&L'!AK7 -> -669043.47
A8: Décaissements OPEX | D8: ='P&L'!B17 -> -2805583 | E8: ='P&L'!C17 -> -2805583 | F8: ='P&L'!D17 -> -2805583 | G8: ='P&L'!E17 -> -2805583 | H8: ='P&L'!F17 -> -2805583 | I8: ='P&L'!G17 -> -2805583 | J8: ='P&L'!H17 -> -2805583 | K8: ='P&L'!I17 -> -2805583 | ... AM8: ='P&L'!AK17 -> -3956412.8
A9: Intérêts payés | D9: ='P&L'!B22 -> -322562.31 | E9: ='P&L'!C22 -> -318285.66 | F9: ='P&L'!D22 -> -313976.94 | G9: ='P&L'!E22 -> -309635.9 | H9: ='P&L'!F22 -> -305262.31 | I9: ='P&L'!G22 -> -300855.91 | J9: ='P&L'!H22 -> -296416.47 | K9: ='P&L'!I22 -> -291943.73 | ... AM9: ='P&L'!AK22 -> -152121.67
A10: Impôts payés | D10: ='P&L'!B24 -> 0 | E10: ='P&L'!C24 -> 0 | F10: ='P&L'!D24 -> 0 | G10: ='P&L'!E24 -> 0 | H10: ='P&L'!F24 -> 0 | I10: ='P&L'!G24 -> 0 | J10: ='P&L'!H24 -> 0 | K10: ='P&L'!I24 -> 0 | ... AM10: ='P&L'!AK24 -> -3172760.8
A11: Flux net opérationnel | C11: 0 | D11: =SUM(D6:D10) -> -2152158.8 | E11: =SUM(E6:E10) -> -1964012.3 | F11: =SUM(F6:F10) -> -1902345 | G11: =SUM(G6:G10) -> -1838246 | H11: =SUM(H6:H10) -> -1771584 | I11: =SUM(I6:I10) -> -1702221.8 | J11: =SUM(J6:J10) -> -1570892 | K11: =SUM(K6:K10) -> -1494508.5 | ... AM11: =SUM(AM6:AM10) -> -1598695.5
A13: FLUX D'INVESTISSEMENT
A14: Acquisition d'immobilisations (CAPEX) | C14: =-Financement!B4 -> -4900000 | D14: =0 -> 0 | E14: =0 -> 0 | F14: =0 -> 0 | G14: =0 -> 0 | H14: =0 -> 0 | I14: =0 -> 0 | J14: =0 -> 0 | K14: =0 -> 0 | ... AM14: =0 -> 0
A15: Flux net d'investissement | C15: =C14 -> -4900000 | D15: =D14 -> 0 | E15: =E14 -> 0 | F15: =F14 -> 0 | G15: =G14 -> 0 | H15: =H14 -> 0 | I15: =I14 -> 0 | J15: =J14 -> 0 | ... AM15: =AM14 -> 0
A17: FLUX DE FINANCEMENT
A18: Apport en fonds propres | C18: =Financement!B14 -> 9000000 | D18: =0 -> 0 | E18: =0 -> 0 | F18: =0 -> 0 | G18: =0 -> 0 | H18: =0 -> 0 | I18: =0 -> 0 | J18: =0 -> 0 | K18: =0 -> 0 | ... AM18: =0 -> 0
A19: Emprunt reçu | C19: =Financement!B15 -> 43008307 | D19: =0 -> 0 | E19: =0 -> 0 | F19: =0 -> 0 | G19: =0 -> 0 | H19: =0 -> 0 | I19: =0 -> 0 | J19: =0 -> 0 | K19: =0 -> 0 | ... AM19: =0 -> 0
A20: Remboursement du capital de l'emprunt | D20: =-Financement!C33 -> -570219.42 | E20: =-Financement!D33 -> -574496.06 | F20: =-Financement!E33 -> -578804.78 | G20: =-Financement!F33 -> -583145.82 | H20: =-Financement!G33 -> -587519.41 | I20: =-Financement!H33 -> -591925.81 | J20: =-Financement!I33 -> -596365.25 | K20: =-Financement!J33 -> -600837.99 | ... AM20: =-Financement!AL33 -> -740660.05
A21: Flux net de financement | C21: =SUM(C18:C20) -> 52008307 | D21: =SUM(D18:D20) -> -570219.42 | E21: =SUM(E18:E20) -> -574496.06 | F21: =SUM(F18:F20) -> -578804.78 | G21: =SUM(G18:G20) -> -583145.82 | H21: =SUM(H18:H20) -> -587519.41 | I21: =SUM(I18:I20) -> -591925.81 | J21: =SUM(J18:J20) -> -596365.25 | ... AM21: =SUM(AM18:AM20) -> -740660.05
A23: FLUX DE TRÉSORERIE NET | C23: =C11+C15+C21 -> 47108307 | D23: =D11+D15+D21 -> -2722378.3 | E23: =E11+E15+E21 -> -2538508.3 | F23: =F11+F15+F21 -> -2481149.8 | G23: =G11+G15+G21 -> -2421391.8 | H23: =H11+H15+H21 -> -2359103.4 | I23: =I11+I15+I21 -> -2294147.6 | J23: =J11+J15+J21 -> -2167257.2 | ... AM23: =AM11+AM15+AM21 -> -2339355.6
A24: Trésorerie d'ouverture | C24: 0 | D24: =C25 -> 47108307 | E24: =D25 -> 44385929 | F24: =E25 -> 41847421 | G24: =F25 -> 39366271 | H24: =G25 -> 36944879 | I24: =H25 -> 34585776 | J24: =I25 -> 32291628 | K24: =J25 -> 30124371 | ... AM24: =AL25 -> -105688.06
A25: TRÉSORERIE DE CLÔTURE | C25: =C23+C24 -> 47108307 | D25: =D23+D24 -> 44385929 | E25: =E23+E24 -> 41847421 | F25: =F23+F24 -> 39366271 | G25: =G23+G24 -> 36944879 | H25: =H23+H24 -> 34585776 | I25: =I23+I24 -> 32291628 | J25: =J23+J24 -> 30124371 | ... AM25: =AM23+AM24 -> -2445043.6
A27: Burn mensuel (op. + inv., si négatif) | D27: =MAX(0,-(D11+D15)) -> 2152158.8 | E27: =MAX(0,-(E11+E15)) -> 1964012.3 | F27: =MAX(0,-(F11+F15)) -> 1902345 | G27: =MAX(0,-(G11+G15)) -> 1838246 | H27: =MAX(0,-(H11+H15)) -> 1771584 | I27: =MAX(0,-(I11+I15)) -> 1702221.8 | J27: =MAX(0,-(J11+J15)) -> 1570892 | K27: =MAX(0,-(K11+K15)) -> 1494508.5 | ... AM27: =MAX(0,-(AM11+AM15)) -> 1598695.5
A28: Runway (mois de trésorerie au rythme du mois) | D28: =IF(D27>0,D25/D27,"∞") -> 20.623909 | E28: =IF(E27>0,E25/E27,"∞") -> 21.307108 | F28: =IF(F27>0,F25/F27,"∞") -> 20.69355 | G28: =IF(G27>0,G25/G27,"∞") -> 20.097898 | H28: =IF(H27>0,H25/H27,"∞") -> 19.522515 | I28: =IF(I27>0,I25/I27,"∞") -> 18.970282 | J28: =IF(J27>0,J25/J27,"∞") -> 19.176602 | K28: =IF(K27>0,K25/K27,"∞") -> 18.754677 | ... AM28: =IF(AM27>0,AM25/AM27,"∞") -> -1.5293992
A30: Choix IAS 7 : intérêts payés classés en flux opérationnels ; le remboursement du capital en flux de financement. Modèle 100 % cash (Mobile Money) : pas de délai de paiement clients.

Sheet KPI
A1: KPI MARKETPLACE — mensuels M1–M36 (MGA) et synthèse annuelle
A2: Année | B2: ='Plan ventes'!B2 -> 1 | C2: ='Plan ventes'!C2 -> 1 | D2: ='Plan ventes'!D2 -> 1 | E2: ='Plan ventes'!E2 -> 1 | F2: ='Plan ventes'!F2 -> 1 | G2: ='Plan ventes'!G2 -> 1 | H2: ='Plan ventes'!H2 -> 1 | I2: ='Plan ventes'!I2 -> 1 | ... AK2: ='Plan ventes'!AK2 -> 3
A3: Mois | B3: ='Plan ventes'!B3 -> 1 | C3: ='Plan ventes'!C3 -> 2 | D3: ='Plan ventes'!D3 -> 3 | E3: ='Plan ventes'!E3 -> 4 | F3: ='Plan ventes'!F3 -> 5 | G3: ='Plan ventes'!G3 -> 6 | H3: ='Plan ventes'!H3 -> 7 | I3: ='Plan ventes'!I3 -> 8 | ... AK3: ='Plan ventes'!AK3 -> 36
A5: CROISSANCE & VOLUME D'AFFAIRES
A6: GMV (volume d'affaires brut) | B6: ='Plan ventes'!B60 -> 2970000 | C6: ='Plan ventes'!C60 -> 3028350 | D6: ='Plan ventes'!D60 -> 3087849.9 | E6: ='Plan ventes'!E60 -> 3148522.4 | F6: ='Plan ventes'!F60 -> 3210390.7 | G6: ='Plan ventes'!G60 -> 3273478.4 | H6: ='Plan ventes'!H60 -> 3337809.6 | I6: ='Plan ventes'!I60 -> 3403408.9 | ... AK6: ='Plan ventes'!AK60 -> 7369664.5
A7: Chiffre d'affaires net (IFRS 15, après stress) | B7: ='P&L'!B5 -> 1394700 | C7: ='P&L'!C5 -> 1455388.4 | D7: ='P&L'!D5 -> 1518457.2 | E7: ='P&L'!E5 -> 1584033.8 | F7: ='P&L'!F5 -> 1652252 | G7: ='P&L'!G5 -> 1723251.5 | H7: ='P&L'!H5 -> 1856302 | I7: ='P&L'!I5 -> 1934492.3 | ... AK7: ='P&L'!AK5 -> 6351643.2
A8: Take rate effectif (CA transactionnel / GMV) | B8: =IF('Plan ventes'!B60=0,0,'Plan ventes'!B62/'Plan ventes'!B60) -> 0.12616162 | C8: =IF('Plan ventes'!C60=0,0,'Plan ventes'!C62/'Plan ventes'!C60) -> 0.12613748 | D8: =IF('Plan ventes'!D60=0,0,'Plan ventes'!D62/'Plan ventes'!D60) -> 0.12611337 | E8: =IF('Plan ventes'!E60=0,0,'Plan ventes'!E62/'Plan ventes'!E60) -> 0.12608929 | F8: =IF('Plan ventes'!F60=0,0,'Plan ventes'!F62/'Plan ventes'!F60) -> 0.12606525 | G8: =IF('Plan ventes'!G60=0,0,'Plan ventes'!G62/'Plan ventes'!G60) -> 0.12604124 | H8: =IF('Plan ventes'!H60=0,0,'Plan ventes'!H62/'Plan ventes'!H60) -> 0.14373054 | I8: =IF('Plan ventes'!I60=0,0,'Plan ventes'!I62/'Plan ventes'!I60) -> 0.14371262 | ... AK8: =IF('Plan ventes'!AK60=0,0,'Plan ventes'!AK62/'Plan ventes'!AK60) -> 0.14346449
A9: MRR (abonnements + vidéo) | B9: ='Plan ventes'!B61 -> 1020000 | C9: ='Plan ventes'!C61 -> 1073400 | D9: ='Plan ventes'!D61 -> 1129038 | E9: ='Plan ventes'!E61 -> 1187038.9 | F9: ='Plan ventes'!F61 -> 1247533.3 | G9: ='Plan ventes'!G61 -> 1310658.2 | H9: ='Plan ventes'!H61 -> 1376556.9 | I9: ='Plan ventes'!I61 -> 1445379.5 | ... AK9: ='Plan ventes'!AK61 -> 5294358.1
A10: ARR (MRR × 12) | B10: =B9*12 -> 12240000 | C10: =C9*12 -> 12880800 | D10: =D9*12 -> 13548456 | E10: =E9*12 -> 14244466 | F10: =F9*12 -> 14970400 | G10: =G9*12 -> 15727898 | H10: =H9*12 -> 16518682 | I10: =I9*12 -> 17344554 | ... AK10: =AK9*12 -> 63532297
A11: Croissance CA (MoM) | B11: =0 -> 0 | C11: =IF(B7=0,0,C7/B7-1) -> 0.043513605 | D11: =IF(C7=0,0,D7/C7-1) -> 0.043334636 | E11: =IF(D7=0,0,E7/D7-1) -> 0.043186386 | F11: =IF(E7=0,0,F7/E7-1) -> 0.043066114 | G11: =IF(F7=0,0,G7/F7-1) -> 0.042971325 | H11: =IF(G7=0,0,H7/G7-1) -> 0.077209025 | I11: =IF(H7=0,0,I7/H7-1) -> 0.042121522 | J11: =IF(I7=0,0,J7/I7-1) -> 0.042106692 | ... AK11: =IF(AJ7=0,0,AK7/AJ7-1) -> 0.034708414
A12: Budget publicité du mois | B12: ='Plan ventes'!B6 -> 400000 | C12: ='Plan ventes'!C6 -> 400000 | D12: ='Plan ventes'!D6 -> 400000 | E12: ='Plan ventes'!E6 -> 400000 | F12: ='Plan ventes'!F6 -> 400000 | G12: ='Plan ventes'!G6 -> 400000 | H12: ='Plan ventes'!H6 -> 400000 | I12: ='Plan ventes'!I6 -> 400000 | ... AK12: ='Plan ventes'!AK6 -> 600000
A13: Multiplicateur de croissance (acquisition) | B13: ='Plan ventes'!B7 -> 1 | C13: ='Plan ventes'!C7 -> 1 | D13: ='Plan ventes'!D7 -> 1 | E13: ='Plan ventes'!E7 -> 1 | F13: ='Plan ventes'!F7 -> 1 | G13: ='Plan ventes'!G7 -> 1 | H13: ='Plan ventes'!H7 -> 1 | I13: ='Plan ventes'!I7 -> 1 | ... AK13: ='Plan ventes'!AK7 -> 1.2247449
A15: OFFRE & LIQUIDITÉ (capacité contraignante)
A16: Prestataires Ampio actifs | B16: ='Plan ventes'!B13 -> 25 | C16: ='Plan ventes'!C13 -> 27.25 | D16: ='Plan ventes'!D13 -> 29.4325 | E16: ='Plan ventes'!E13 -> 31.549525 | F16: ='Plan ventes'!F13 -> 33.603039 | G16: ='Plan ventes'!G13 -> 35.594948 | H16: ='Plan ventes'!H13 -> 37.5271 | I16: ='Plan ventes'!I13 -> 39.401287 | ... AK16: ='Plan ventes'!AK13 -> 121.62289
A17: Utilisation de la capacité Ampio (alerte si ≥ fill rate max) | B17: ='Plan ventes'!B21 -> 0.375 | C17: ='Plan ventes'!C21 -> 0.35091743 | D17: ='Plan ventes'!D21 -> 0.33139387 | E17: ='Plan ventes'!E21 -> 0.31533993 | F17: ='Plan ventes'!F21 -> 0.30199059 | G17: ='Plan ventes'!G21 -> 0.29079288 | H17: ='Plan ventes'!H21 -> 0.28133729 | I17: ='Plan ventes'!I21 -> 0.27331412 | ... AK17: ='Plan ventes'!AK21 -> 0.1663472
A18: Prestations non servies (pénurie d'offre) | B18: ='Plan ventes'!B20 -> 0 | C18: ='Plan ventes'!C20 -> 0 | D18: ='Plan ventes'!D20 -> 0 | E18: ='Plan ventes'!E20 -> 0 | F18: ='Plan ventes'!F20 -> 0 | G18: ='Plan ventes'!G20 -> 0 | H18: ='Plan ventes'!H20 -> 0 | I18: ='Plan ventes'!I20 -> 0 | ... AK18: ='Plan ventes'!AK20 -> 0
A19: GMV perdu faute d'offre (tous segments) | B19: ='Plan ventes'!B67 -> 0 | C19: ='Plan ventes'!C67 -> 0 | D19: ='Plan ventes'!D67 -> 0 | E19: ='Plan ventes'!E67 -> 0 | F19: ='Plan ventes'!F67 -> 0 | G19: ='Plan ventes'!G67 -> 0 | H19: ='Plan ventes'!H67 -> 0 | I19: ='Plan ventes'!I67 -> 0 | ... AK19: ='Plan ventes'!AK67 -> 0
A20: Loueurs pro actifs | B20: ='Plan ventes'!B36 -> 8 | C20: ='Plan ventes'!C36 -> 8.84 | D20: ='Plan ventes'!D36 -> 9.6632 | E20: ='Plan ventes'!E36 -> 10.469936 | F20: ='Plan ventes'!F36 -> 11.260537 | G20: ='Plan ventes'!G36 -> 12.035327 | H20: ='Plan ventes'!H36 -> 12.79462 | I20: ='Plan ventes'!I36 -> 13.538728 | ... AK20: ='Plan ventes'!AK36 -> 39.254298
A21: Utilisation capacité locations pro | B21: ='Plan ventes'!B41 -> 0.46875 | C21: ='Plan ventes'!C41 -> 0.43184389 | D21: ='Plan ventes'!D41 -> 0.40216647 | E21: ='Plan ventes'!E41 -> 0.3778597 | F21: ='Plan ventes'!F41 -> 0.35765415 | G21: ='Plan ventes'!G41 -> 0.34065305 | H21: ='Plan ventes'!H41 -> 0.32620495 | I21: ='Plan ventes'!I41 -> 0.31382524 | ... AK21: ='Plan ventes'!AK41 -> 0.19613897
A22: Annonces C2C actives | B22: ='Plan ventes'!B49 -> 15 | C22: ='Plan ventes'!C49 -> 16.25 | D22: ='Plan ventes'!D49 -> 17.4375 | E22: ='Plan ventes'!E49 -> 18.565625 | F22: ='Plan ventes'!F49 -> 19.637344 | G22: ='Plan ventes'!G49 -> 20.655477 | H22: ='Plan ventes'!H49 -> 21.622703 | I22: ='Plan ventes'!I49 -> 22.541568 | ... AK22: ='Plan ventes'!AK49 -> 35.847915
A23: Utilisation capacité C2C | B23: ='Plan ventes'!B54 -> 0.8 | C23: ='Plan ventes'!C54 -> 0.74953846 | D23: ='Plan ventes'!D54 -> 0.70897204 | E23: ='Plan ventes'!E54 -> 0.67588032 | F23: ='Plan ventes'!F54 -> 0.64857869 | G23: ='Plan ventes'!G54 -> 0.62585862 | H23: ='Plan ventes'!H54 -> 0.60683067 | I23: ='Plan ventes'!I54 -> 0.59082577 | ... AK23: ='Plan ventes'!AK54 -> 0.53416297
A24: Collaborateur 2 actif (0/1) | B24: ='Plan ventes'!B70 -> 0 | C24: ='Plan ventes'!C70 -> 0 | D24: ='Plan ventes'!D70 -> 0 | E24: ='Plan ventes'!E70 -> 0 | F24: ='Plan ventes'!F70 -> 0 | G24: ='Plan ventes'!G70 -> 0 | H24: ='Plan ventes'!H70 -> 0 | I24: ='Plan ventes'!I70 -> 0 | ... AK24: ='Plan ventes'!AK70 -> 1
A26: UNIT ECONOMICS PAR FACE (offre / demande) — LTV bornée à 36 mois, commissions partagées 50/50 entre les faces
A27: Nouveaux OFFRE (prestataires + loueurs pro onboardés) | B27: ='Plan ventes'!B11+'Plan ventes'!B34 -> 33 | C27: ='Plan ventes'!C11+'Plan ventes'!C34 -> 4 | D27: ='Plan ventes'!D11+'Plan ventes'!D34 -> 4 | E27: ='Plan ventes'!E11+'Plan ventes'!E34 -> 4 | F27: ='Plan ventes'!F11+'Plan ventes'!F34 -> 4 | G27: ='Plan ventes'!G11+'Plan ventes'!G34 -> 4 | H27: ='Plan ventes'!H11+'Plan ventes'!H34 -> 4 | I27: ='Plan ventes'!I11+'Plan ventes'!I34 -> 4 | ... AK27: ='Plan ventes'!AK11+'Plan ventes'!AK34 -> 10
A28: Nouveaux DEMANDE (clients vidéo + clients transactionnels estimés) | B28: ='Plan ventes'!B27+'Plan ventes'!B65 -> 30.3 | C28: ='Plan ventes'!C27+'Plan ventes'!C65 -> 16.7175 | D28: ='Plan ventes'!D27+'Plan ventes'!D65 -> 17.071884 | E28: ='Plan ventes'!E27+'Plan ventes'!E65 -> 17.434824 | F28: ='Plan ventes'!F27+'Plan ventes'!F65 -> 17.806571 | G28: ='Plan ventes'!G27+'Plan ventes'!G65 -> 18.187387 | H28: ='Plan ventes'!H27+'Plan ventes'!H65 -> 18.577543 | I28: ='Plan ventes'!I27+'Plan ventes'!I65 -> 18.977319 | ... AK28: ='Plan ventes'!AK27+'Plan ventes'!AK65 -> 35.721955
A29: Dépenses d'acquisition (pub + part accompagnement + temps fondateur chargé) | B29: ='Plan ventes'!B6+Parametres!$D$120*(1+Parametres!$D$47)^(B$2-1)*Parametres!$D$70+Parametres!$D$71*Parametres!$D$113*(1+Parametres!$D$115)*(1+Parametres!$D$47)^(B$2-1) -> 763200 | C29: ='Plan ventes'!C6+Parametres!$D$120*(1+Parametres!$D$47)^(C$2-1)*Parametres!$D$70+Parametres!$D$71*Parametres!$D$113*(1+Parametres!$D$115)*(1+Parametres!$D$47)^(C$2-1) -> 763200 | D29: ='Plan ventes'!D6+Parametres!$D$120*(1+Parametres!$D$47)^(D$2-1)*Parametres!$D$70+Parametres!$D$71*Parametres!$D$113*(1+Parametres!$D$115)*(1+Parametres!$D$47)^(D$2-1) -> 763200 | E29: ='Plan ventes'!E6+Parametres!$D$120*(1+Parametres!$D$47)^(E$2-1)*Parametres!$D$70+Parametres!$D$71*Parametres!$D$113*(1+Parametres!$D$115)*(1+Parametres!$D$47)^(E$2-1) -> 763200 | F29: ='Plan ventes'!F6+Parametres!$D$120*(1+Parametres!$D$47)^(F$2-1)*Parametres!$D$70+Parametres!$D$71*Parametres!$D$113*(1+Parametres!$D$115)*(1+Parametres!$D$47)^(F$2-1) -> 763200 | G29: ='Plan ventes'!G6+Parametres!$D$120*(1+Parametres!$D$47)^(G$2-1)*Parametres!$D$70+Parametres!$D$71*Parametres!$D$113*(1+Parametres!$D$115)*(1+Parametres!$D$47)^(G$2-1) -> 763200 | H29: ='Plan ventes'!H6+Parametres!$D$120*(1+Parametres!$D$47)^(H$2-1)*Parametres!$D$70+Parametres!$D$71*Parametres!$D$113*(1+Parametres!$D$115)*(1+Parametres!$D$47)^(H$2-1) -> 763200 | I29: ='Plan ventes'!I6+Parametres!$D$120*(1+Parametres!$D$47)^(I$2-1)*Parametres!$D$70+Parametres!$D$71*Parametres!$D$113*(1+Parametres!$D$115)*(1+Parametres!$D$47)^(I$2-1) -> 763200 | ... AK29: ='Plan ventes'!AK6+Parametres!$D$120*(1+Parametres!$D$47)^(AK$2-1)*Parametres!$D$70+Parametres!$D$71*Parametres!$D$113*(1+Parametres!$D$115)*(1+Parametres!$D$47)^(AK$2-1) -> 1023636.5
A30: Dépenses d'acquisition OFFRE | B30: =Parametres!$D$76*B29 -> 228960 | C30: =Parametres!$D$76*C29 -> 228960 | D30: =Parametres!$D$76*D29 -> 228960 | E30: =Parametres!$D$76*E29 -> 228960 | F30: =Parametres!$D$76*F29 -> 228960 | G30: =Parametres!$D$76*G29 -> 228960 | H30: =Parametres!$D$76*H29 -> 228960 | I30: =Parametres!$D$76*I29 -> 228960 | ... AK30: =Parametres!$D$76*AK29 -> 307090.94
A31: Dépenses d'acquisition DEMANDE | B31: =Parametres!$D$75*B29 -> 534240 | C31: =Parametres!$D$75*C29 -> 534240 | D31: =Parametres!$D$75*D29 -> 534240 | E31: =Parametres!$D$75*E29 -> 534240 | F31: =Parametres!$D$75*F29 -> 534240 | G31: =Parametres!$D$75*G29 -> 534240 | H31: =Parametres!$D$75*H29 -> 534240 | I31: =Parametres!$D$75*I29 -> 534240 | ... AK31: =Parametres!$D$75*AK29 -> 716545.54
A32: CAC offre | B32: =IF(B27=0,0,B30/B27) -> 6938.1818 | C32: =IF(C27=0,0,C30/C27) -> 57240 | D32: =IF(D27=0,0,D30/D27) -> 57240 | E32: =IF(E27=0,0,E30/E27) -> 57240 | F32: =IF(F27=0,0,F30/F27) -> 57240 | G32: =IF(G27=0,0,G30/G27) -> 57240 | H32: =IF(H27=0,0,H30/H27) -> 57240 | I32: =IF(I27=0,0,I30/I27) -> 57240 | ... AK32: =IF(AK27=0,0,AK30/AK27) -> 30709.094
A33: CAC demande | B33: =IF(B28=0,0,B31/B28) -> 17631.683 | C33: =IF(C28=0,0,C31/C28) -> 31956.931 | D33: =IF(D28=0,0,D31/D28) -> 31293.558 | E33: =IF(E28=0,0,E31/E28) -> 30642.122 | F33: =IF(F28=0,0,F31/F28) -> 30002.407 | G33: =IF(G28=0,0,G31/G28) -> 29374.203 | H33: =IF(H28=0,0,H31/H28) -> 28757.301 | I33: =IF(I28=0,0,I31/I28) -> 28151.5 | ... AK33: =IF(AK28=0,0,AK31/AK28) -> 20058.967
A34: Revenu mensuel moyen par prestataire / loueur (50 % commissions + abonnements Ampio+) | B34: =IF('Plan ventes'!B13+'Plan ventes'!B36=0,0,(0.5*('Plan ventes'!B24+'Plan ventes'!B44)+'Plan ventes'!B17)/('Plan ventes'!B13+'Plan ventes'!B36)) -> 7259.0909 | C34: =IF('Plan ventes'!C13+'Plan ventes'!C36=0,0,(0.5*('Plan ventes'!C24+'Plan ventes'!C44)+'Plan ventes'!C17)/('Plan ventes'!C13+'Plan ventes'!C36)) -> 6884.9325 | D34: =IF('Plan ventes'!D13+'Plan ventes'!D36=0,0,(0.5*('Plan ventes'!D24+'Plan ventes'!D44)+'Plan ventes'!D17)/('Plan ventes'!D13+'Plan ventes'!D36)) -> 6581.5888 | E34: =IF('Plan ventes'!E13+'Plan ventes'!E36=0,0,(0.5*('Plan ventes'!E24+'Plan ventes'!E44)+'Plan ventes'!E17)/('Plan ventes'!E13+'Plan ventes'!E36)) -> 6331.8293 | F34: =IF('Plan ventes'!F13+'Plan ventes'!F36=0,0,(0.5*('Plan ventes'!F24+'Plan ventes'!F44)+'Plan ventes'!F17)/('Plan ventes'!F13+'Plan ventes'!F36)) -> 6123.6316 | G34: =IF('Plan ventes'!G13+'Plan ventes'!G36=0,0,(0.5*('Plan ventes'!G24+'Plan ventes'!G44)+'Plan ventes'!G17)/('Plan ventes'!G13+'Plan ventes'!G36)) -> 5948.3534 | H34: =IF('Plan ventes'!H13+'Plan ventes'!H36=0,0,(0.5*('Plan ventes'!H24+'Plan ventes'!H44)+'Plan ventes'!H17)/('Plan ventes'!H13+'Plan ventes'!H36)) -> 6387.0785 | I34: =IF('Plan ventes'!I13+'Plan ventes'!I36=0,0,(0.5*('Plan ventes'!I24+'Plan ventes'!I44)+'Plan ventes'!I17)/('Plan ventes'!I13+'Plan ventes'!I36)) -> 6242.2103 | ... AK34: =IF('Plan ventes'!AK13+'Plan ventes'!AK36=0,0,(0.5*('Plan ventes'!AK24+'Plan ventes'!AK44)+'Plan ventes'!AK17)/('Plan ventes'!AK13+'Plan ventes'!AK36)) -> 5312.0714
A35: Durée de vie offre (mois) = MIN(36 ; 1 / churn prestataires) | B35: =MIN(36,IF(Parametres!$D$84=0,36,1/Parametres!$D$84)) -> 33.333333 | C35: =MIN(36,IF(Parametres!$D$84=0,36,1/Parametres!$D$84)) -> 33.333333 | D35: =MIN(36,IF(Parametres!$D$84=0,36,1/Parametres!$D$84)) -> 33.333333 | E35: =MIN(36,IF(Parametres!$D$84=0,36,1/Parametres!$D$84)) -> 33.333333 | F35: =MIN(36,IF(Parametres!$D$84=0,36,1/Parametres!$D$84)) -> 33.333333 | G35: =MIN(36,IF(Parametres!$D$84=0,36,1/Parametres!$D$84)) -> 33.333333 | H35: =MIN(36,IF(Parametres!$D$84=0,36,1/Parametres!$D$84)) -> 33.333333 | I35: =MIN(36,IF(Parametres!$D$84=0,36,1/Parametres!$D$84)) -> 33.333333 | ... AK35: =MIN(36,IF(Parametres!$D$84=0,36,1/Parametres!$D$84)) -> 33.333333
A36: LTV offre (revenu mensuel × durée de vie bornée) | B36: =B34*B35 -> 241969.7 | C36: =C34*C35 -> 229497.75 | D36: =D34*D35 -> 219386.29 | E36: =E34*E35 -> 211060.98 | F36: =F34*F35 -> 204121.05 | G36: =G34*G35 -> 198278.45 | H36: =H34*H35 -> 212902.62 | I36: =I34*I35 -> 208073.68 | ... AK36: =AK34*AK35 -> 177069.05
A37: LTV demande (vidéo : prix × MIN(36 ; 1/churn) ; transactionnel : 50 % commission par transaction × tx/client × durée de vie) | B37: =IF(B28=0,0,('Plan ventes'!B27*'Plan ventes'!B30*MIN(36,IF(Parametres!$D$25=0,36,1/Parametres!$D$25))+'Plan ventes'!B65*0.5*IF('Plan ventes'!B64=0,0,'Plan ventes'!B62/'Plan ventes'!B64)*Parametres!$D$73*Parametres!$D$74)/B28) -> 1142449 | C37: =IF(C28=0,0,('Plan ventes'!C27*'Plan ventes'!C30*MIN(36,IF(Parametres!$D$25=0,36,1/Parametres!$D$25))+'Plan ventes'!C65*0.5*IF('Plan ventes'!C64=0,0,'Plan ventes'!C62/'Plan ventes'!C64)*Parametres!$D$73*Parametres!$D$74)/C28) -> 158474.55 | D37: =IF(D28=0,0,('Plan ventes'!D27*'Plan ventes'!D30*MIN(36,IF(Parametres!$D$25=0,36,1/Parametres!$D$25))+'Plan ventes'!D65*0.5*IF('Plan ventes'!D64=0,0,'Plan ventes'!D62/'Plan ventes'!D64)*Parametres!$D$73*Parametres!$D$74)/D28) -> 162841.6 | E37: =IF(E28=0,0,('Plan ventes'!E27*'Plan ventes'!E30*MIN(36,IF(Parametres!$D$25=0,36,1/Parametres!$D$25))+'Plan ventes'!E65*0.5*IF('Plan ventes'!E64=0,0,'Plan ventes'!E62/'Plan ventes'!E64)*Parametres!$D$73*Parametres!$D$74)/E28) -> 167321.98 | F37: =IF(F28=0,0,('Plan ventes'!F27*'Plan ventes'!F30*MIN(36,IF(Parametres!$D$25=0,36,1/Parametres!$D$25))+'Plan ventes'!F65*0.5*IF('Plan ventes'!F64=0,0,'Plan ventes'!F62/'Plan ventes'!F64)*Parametres!$D$73*Parametres!$D$74)/F28) -> 171918.1 | G37: =IF(G28=0,0,('Plan ventes'!G27*'Plan ventes'!G30*MIN(36,IF(Parametres!$D$25=0,36,1/Parametres!$D$25))+'Plan ventes'!G65*0.5*IF('Plan ventes'!G64=0,0,'Plan ventes'!G62/'Plan ventes'!G64)*Parametres!$D$73*Parametres!$D$74)/G28) -> 176632.36 | H37: =IF(H28=0,0,('Plan ventes'!H27*'Plan ventes'!H30*MIN(36,IF(Parametres!$D$25=0,36,1/Parametres!$D$25))+'Plan ventes'!H65*0.5*IF('Plan ventes'!H64=0,0,'Plan ventes'!H62/'Plan ventes'!H64)*Parametres!$D$73*Parametres!$D$74)/H28) -> 181944.6 | I37: =IF(I28=0,0,('Plan ventes'!I27*'Plan ventes'!I30*MIN(36,IF(Parametres!$D$25=0,36,1/Parametres!$D$25))+'Plan ventes'!I65*0.5*IF('Plan ventes'!I64=0,0,'Plan ventes'!I62/'Plan ventes'!I64)*Parametres!$D$73*Parametres!$D$74)/I28) -> 186901.79 | ... AK37: =IF(AK28=0,0,('Plan ventes'!AK27*'Plan ventes'!AK30*MIN(36,IF(Parametres!$D$25=0,36,1/Parametres!$D$25))+'Plan ventes'!AK65*0.5*IF('Plan ventes'!AK64=0,0,'Plan ventes'!AK62/'Plan ventes'!AK64)*Parametres!$D$73*Parametres!$D$74)/AK28) -> 301760.99
A38: LTV / CAC offre (cible indicative > 3) | B38: =IF(B32=0,0,B36/B32) -> 34.875087 | C38: =IF(C32=0,0,C36/C32) -> 4.0093946 | D38: =IF(D32=0,0,D36/D32) -> 3.8327445 | E38: =IF(E32=0,0,E36/E32) -> 3.6872987 | F38: =IF(F32=0,0,F36/F32) -> 3.5660562 | G38: =IF(G32=0,0,G36/G32) -> 3.4639841 | H38: =IF(H32=0,0,H36/H32) -> 3.7194727 | I38: =IF(I32=0,0,I36/I32) -> 3.6351096 | ... AK38: =IF(AK32=0,0,AK36/AK32) -> 5.7660133
A39: LTV / CAC demande (cible indicative > 3) | B39: =IF(B33=0,0,B37/B33) -> 64.795232 | C39: =IF(C33=0,0,C37/C33) -> 4.9590039 | D39: =IF(D33=0,0,D37/D33) -> 5.2036779 | E39: =IF(E33=0,0,E37/E33) -> 5.4605219 | F39: =IF(F33=0,0,F37/F33) -> 5.7301434 | G39: =IF(G33=0,0,G37/G33) -> 6.0131798 | H39: =IF(H33=0,0,H37/H33) -> 6.326901 | I39: =IF(I33=0,0,I37/I33) -> 6.6391413 | ... AK39: =IF(AK33=0,0,AK37/AK33) -> 15.043695
A40: Payback CAC offre (mois) = CAC / revenu mensuel par prestataire | B40: =IF(B34=0,0,B32/B34) -> 0.95579211 | C40: =IF(C34=0,0,C32/C34) -> 8.313807 | D40: =IF(D34=0,0,D32/D34) -> 8.6969882 | E40: =IF(E34=0,0,E32/E34) -> 9.0400416 | F40: =IF(F34=0,0,F32/F34) -> 9.3473944 | G40: =IF(G34=0,0,G32/G34) -> 9.6228311 | H40: =IF(H34=0,0,H32/H34) -> 8.9618439 | I40: =IF(I34=0,0,I32/I34) -> 9.1698289 | ... AK40: =IF(AK34=0,0,AK32/AK34) -> 5.7810018
A42: TRÉSORERIE & LIQUIDITÉ FINANCIÈRE
A43: Trésorerie de clôture | B43: =Tresorerie!D25 -> 44385929 | C43: =Tresorerie!E25 -> 41847421 | D43: =Tresorerie!F25 -> 39366271 | E43: =Tresorerie!G25 -> 36944879 | F43: =Tresorerie!H25 -> 34585776 | G43: =Tresorerie!I25 -> 32291628 | H43: =Tresorerie!J25 -> 30124371 | I43: =Tresorerie!K25 -> 28029025 | ... AK43: =Tresorerie!AM25 -> -2445043.6
A44: Burn net mensuel | B44: =Tresorerie!D27 -> 2152158.8 | C44: =Tresorerie!E27 -> 1964012.3 | D44: =Tresorerie!F27 -> 1902345 | E44: =Tresorerie!G27 -> 1838246 | F44: =Tresorerie!H27 -> 1771584 | G44: =Tresorerie!I27 -> 1702221.8 | H44: =Tresorerie!J27 -> 1570892 | I44: =Tresorerie!K27 -> 1494508.5 | ... AK44: =Tresorerie!AM27 -> 1598695.5
A45: Runway (mois) | B45: =Tresorerie!D28 -> 20.623909 | C45: =Tresorerie!E28 -> 21.307108 | D45: =Tresorerie!F28 -> 20.69355 | E45: =Tresorerie!G28 -> 20.097898 | F45: =Tresorerie!H28 -> 19.522515 | G45: =Tresorerie!I28 -> 18.970282 | H45: =Tresorerie!J28 -> 19.176602 | I45: =Tresorerie!K28 -> 18.754677 | ... AK45: =Tresorerie!AM28 -> -1.5293992
A46: Passif courant estimé (capital emprunt ≤ 12 mois + impôt de l'exercice) | B46: =MIN(Financement!C34,12*Financement!$C$31)+CHOOSE('P&L'!B2,'P&L'!$B$34,'P&L'!$C$34,'P&L'!$D$34) -> 11798712 | C46: =MIN(Financement!D34,12*Financement!$C$31)+CHOOSE('P&L'!C2,'P&L'!$B$34,'P&L'!$C$34,'P&L'!$D$34) -> 11798712 | D46: =MIN(Financement!E34,12*Financement!$C$31)+CHOOSE('P&L'!D2,'P&L'!$B$34,'P&L'!$C$34,'P&L'!$D$34) -> 11798712 | E46: =MIN(Financement!F34,12*Financement!$C$31)+CHOOSE('P&L'!E2,'P&L'!$B$34,'P&L'!$C$34,'P&L'!$D$34) -> 11798712 | F46: =MIN(Financement!G34,12*Financement!$C$31)+CHOOSE('P&L'!F2,'P&L'!$B$34,'P&L'!$C$34,'P&L'!$D$34) -> 11798712 | G46: =MIN(Financement!H34,12*Financement!$C$31)+CHOOSE('P&L'!G2,'P&L'!$B$34,'P&L'!$C$34,'P&L'!$D$34) -> 11798712 | H46: =MIN(Financement!I34,12*Financement!$C$31)+CHOOSE('P&L'!H2,'P&L'!$B$34,'P&L'!$C$34,'P&L'!$D$34) -> 11798712 | I46: =MIN(Financement!J34,12*Financement!$C$31)+CHOOSE('P&L'!I2,'P&L'!$B$34,'P&L'!$C$34,'P&L'!$D$34) -> 11798712 | ... AK46: =MIN(Financement!AL34,12*Financement!$C$31)+CHOOSE('P&L'!AK2,'P&L'!$B$34,'P&L'!$C$34,'P&L'!$D$34) -> 13886141
A47: Taux de liquidité générale (trésorerie / passif courant) | B47: =IF(B46=0,"∞",B43/B46) -> 3.7619301 | C47: =IF(C46=0,"∞",C43/C46) -> 3.5467788 | D47: =IF(D46=0,"∞",D43/D46) -> 3.3364889 | E47: =IF(E46=0,"∞",E43/E46) -> 3.1312638 | F47: =IF(F46=0,"∞",F43/F46) -> 2.931318 | G47: =IF(G46=0,"∞",G43/G46) -> 2.7368775 | H47: =IF(H46=0,"∞",H43/H46) -> 2.5531915 | I47: =IF(I46=0,"∞",I43/I46) -> 2.3756004 | ... AK47: =IF(AK46=0,"∞",AK43/AK46) -> -0.17607797
A49: SYNTHÈSE ANNUELLE
B50: Année 1 | C50: Année 2 | D50: Année 3
A51: GMV annuel | B51: =SUMIF($B$2:$AK$2,1,$B$6:$AK$6) -> 39755688 | C51: =SUMIF($B$2:$AK$2,2,$B$6:$AK$6) -> 54904951 | D51: =SUMIF($B$2:$AK$2,3,$B$6:$AK$6) -> 77839858
A52: CA annuel | B52: ='P&L'!B30 -> 21706621 | C52: ='P&L'!C30 -> 38087024 | D52: ='P&L'!D30 -> 63455216
A53: Take rate moyen (CA transactionnel / GMV) | B53: =IF(SUMIF($B$2:$AK$2,1,$B$6:$AK$6)=0,0,SUMIF($B$2:$AK$2,1,'Plan ventes'!$B$62:$AK$62)/SUMIF($B$2:$AK$2,1,$B$6:$AK$6)) -> 0.13540515 | C53: =IF(SUMIF($B$2:$AK$2,2,$B$6:$AK$6)=0,0,SUMIF($B$2:$AK$2,2,'Plan ventes'!$B$62:$AK$62)/SUMIF($B$2:$AK$2,2,$B$6:$AK$6)) -> 0.14351988 | D53: =IF(SUMIF($B$2:$AK$2,3,$B$6:$AK$6)=0,0,SUMIF($B$2:$AK$2,3,'Plan ventes'!$B$62:$AK$62)/SUMIF($B$2:$AK$2,3,$B$6:$AK$6)) -> 0.14343777
A54: MRR fin d'année | B54: =INDEX($B$9:$AK$9,1,12*1) -> 1753171.5 | C54: =INDEX($B$9:$AK$9,1,12*2) -> 3146834.9 | D54: =INDEX($B$9:$AK$9,1,12*3) -> 5294358.1
A55: EBITDA annuel | B55: ='P&L'!B31 -> -15962797 | C55: ='P&L'!C31 -> -4181951.1 | D55: ='P&L'!D31 -> 8893982.1
A56: Résultat net annuel | B56: ='P&L'!B35 -> -21609440 | C56: ='P&L'!C35 -> -9978577.1 | D56: ='P&L'!D35 -> 2560744
A57: Marge EBITDA | B57: =IF(B52=0,0,B55/B52) -> -0.7353884 | C57: =IF(C52=0,0,C55/C52) -> -0.10979989 | D57: =IF(D52=0,0,D55/D52) -> 0.14016156
A58: Croissance CA (YoY) | B58: =0 -> 0 | C58: =IF(B52=0,0,C52/B52-1) -> 0.75462707 | D58: =IF(C52=0,0,D52/C52-1) -> 0.66605866
A59: Prestataires actifs fin d'année | B59: =INDEX($B$16:$AK$16,1,12*1) -> 46.352395 | C59: =INDEX($B$16:$AK$16,1,12*2) -> 62.777019 | D59: =INDEX($B$16:$AK$16,1,12*3) -> 121.62289
A60: Utilisation capacité Ampio fin d'année | B60: =INDEX($B$17:$AK$17,1,12*1) -> 0.25147857 | C60: =INDEX($B$17:$AK$17,1,12*2) -> 0.24155619 | D60: =INDEX($B$17:$AK$17,1,12*3) -> 0.1663472
A61: GMV perdu faute d'offre (annuel) | B61: =SUMIF($B$2:$AK$2,1,$B$19:$AK$19) -> 0 | C61: =SUMIF($B$2:$AK$2,2,$B$19:$AK$19) -> 0 | D61: =SUMIF($B$2:$AK$2,3,$B$19:$AK$19) -> 0
A62: Budget publicité annuel | B62: =SUMIF($B$2:$AK$2,1,$B$12:$AK$12) -> 4800000 | C62: =SUMIF($B$2:$AK$2,2,$B$12:$AK$12) -> 6000000 | D62: =SUMIF($B$2:$AK$2,3,$B$12:$AK$12) -> 7200000
A63: CAC offre moyen annuel | B63: =IF(SUMIF($B$2:$AK$2,1,$B$27:$AK$27)=0,0,SUMIF($B$2:$AK$2,1,$B$30:$AK$30)/SUMIF($B$2:$AK$2,1,$B$27:$AK$27)) -> 35682.078 | C63: =IF(SUMIF($B$2:$AK$2,2,$B$27:$AK$27)=0,0,SUMIF($B$2:$AK$2,2,$B$30:$AK$30)/SUMIF($B$2:$AK$2,2,$B$27:$AK$27)) -> 66919.2 | D63: =IF(SUMIF($B$2:$AK$2,3,$B$27:$AK$27)=0,0,SUMIF($B$2:$AK$2,3,$B$30:$AK$30)/SUMIF($B$2:$AK$2,3,$B$27:$AK$27)) -> 32325.363
A64: CAC demande moyen annuel | B64: =IF(SUMIF($B$2:$AK$2,1,$B$28:$AK$28)=0,0,SUMIF($B$2:$AK$2,1,$B$31:$AK$31)/SUMIF($B$2:$AK$2,1,$B$28:$AK$28)) -> 27259.126 | C64: =IF(SUMIF($B$2:$AK$2,2,$B$28:$AK$28)=0,0,SUMIF($B$2:$AK$2,2,$B$31:$AK$31)/SUMIF($B$2:$AK$2,2,$B$28:$AK$28)) -> 26165.618 | D64: =IF(SUMIF($B$2:$AK$2,3,$B$28:$AK$28)=0,0,SUMIF($B$2:$AK$2,3,$B$31:$AK$31)/SUMIF($B$2:$AK$2,3,$B$28:$AK$28)) -> 22872.079
A65: LTV / CAC offre fin d'année | B65: =INDEX($B$38:$AK$38,1,12*1) -> 3.4007978 | C65: =INDEX($B$38:$AK$38,1,12*2) -> 2.9963031 | D65: =INDEX($B$38:$AK$38,1,12*3) -> 5.7660133
A66: LTV / CAC demande fin d'année | B66: =INDEX($B$39:$AK$39,1,12*1) -> 8.0513685 | C66: =INDEX($B$39:$AK$39,1,12*2) -> 11.655815 | D66: =INDEX($B$39:$AK$39,1,12*3) -> 15.043695
A67: Rule of 40 (croissance CA YoY + marge EBITDA) | B67: =B58+B57 -> -0.7353884 | C67: =C58+C57 -> 0.64482718 | D67: =D58+D57 -> 0.80622022

Sheet Base graphique
A1: BASE GRAPHIQUE — séries mensuelles pour les graphiques du Dashboard
A2: Mois | B2: 1 | C2: 2 | D2: 3 | E2: 4 | F2: 5 | G2: 6 | H2: 7 | I2: 8 | J2: 9 | K2: 10 | L2: 11 | M2: 12 | N2: 13 | O2: 14 | P2: 15 | Q2: 16 | R2: 17 | S2: 18 | T2: 19 | U2: 20 | V2: 21 | W2: 22 | X2: 23 | Y2: 24 | Z2: 25 | AA2: 26 | AB2: 27 | AC2: 28 | AD2: 29 | AE2: 30 | AF2: 31 | AG2: 32 | AH2: 33 | AI2: 34 | AJ2: 35 | AK2: 36
A3: Chiffre d'affaires | B3: ='P&L'!B5 -> 1394700 | C3: ='P&L'!C5 -> 1455388.4 | D3: ='P&L'!D5 -> 1518457.2 | E3: ='P&L'!E5 -> 1584033.8 | F3: ='P&L'!F5 -> 1652252 | G3: ='P&L'!G5 -> 1723251.5 | H3: ='P&L'!H5 -> 1856302 | I3: ='P&L'!I5 -> 1934492.3 | ... AK3: ='P&L'!AK5 -> 6351643.2
A4: Résultat net | B4: ='P&L'!B25 -> -2233825.5 | C4: ='P&L'!C25 -> -2045678.9 | D4: ='P&L'!D25 -> -1984011.6 | E4: ='P&L'!E25 -> -1919912.6 | F4: ='P&L'!F25 -> -1853250.7 | G4: ='P&L'!G25 -> -1783888.5 | H4: ='P&L'!H25 -> -1652558.7 | I4: ='P&L'!I25 -> -1576175.2 | ... AK4: ='P&L'!AK25 -> -1680362.2
A5: Trésorerie de clôture | B5: =Tresorerie!D25 -> 44385929 | C5: =Tresorerie!E25 -> 41847421 | D5: =Tresorerie!F25 -> 39366271 | E5: =Tresorerie!G25 -> 36944879 | F5: =Tresorerie!H25 -> 34585776 | G5: =Tresorerie!I25 -> 32291628 | H5: =Tresorerie!J25 -> 30124371 | I5: =Tresorerie!K25 -> 28029025 | ... AK5: =Tresorerie!AM25 -> -2445043.6
A6: MRR | B6: ='Plan ventes'!B61 -> 1020000 | C6: ='Plan ventes'!C61 -> 1073400 | D6: ='Plan ventes'!D61 -> 1129038 | E6: ='Plan ventes'!E61 -> 1187038.9 | F6: ='Plan ventes'!F61 -> 1247533.3 | G6: ='Plan ventes'!G61 -> 1310658.2 | H6: ='Plan ventes'!H61 -> 1376556.9 | I6: ='Plan ventes'!I61 -> 1445379.5 | ... AK6: ='Plan ventes'!AK61 -> 5294358.1
A7: GMV | B7: ='Plan ventes'!B60 -> 2970000 | C7: ='Plan ventes'!C60 -> 3028350 | D7: ='Plan ventes'!D60 -> 3087849.9 | E7: ='Plan ventes'!E60 -> 3148522.4 | F7: ='Plan ventes'!F60 -> 3210390.7 | G7: ='Plan ventes'!G60 -> 3273478.4 | H7: ='Plan ventes'!H60 -> 3337809.6 | I7: ='Plan ventes'!I60 -> 3403408.9 | ... AK7: ='Plan ventes'!AK60 -> 7369664.5
A8: Résultat net cumulé | B8: =B4 -> -2233825.5 | C8: =B8+C4 -> -4279504.4 | D8: =C8+D4 -> -6263516.1 | E8: =D8+E4 -> -8183428.7 | F8: =E8+F4 -> -10036679 | G8: =F8+G4 -> -11820568 | H8: =G8+H4 -> -13473127 | I8: =H8+I4 -> -15049302 | J8: =I8+J4 -> -16545917 | ... AK8: =AJ8+AK4 -> -29027273
